Workbook

Sheet PICOC & RQs
A1: PICOC Element | B1: Description
A2: Problem | B2: Studies proposing or evaluating hybrid ANN–SNN or pure SNN architectures for neuromorphic or event-driven learning tasks, where spike encoding plays a functional role in the learning pipeline.
A3: Intervention | B3: Introduction or application of learnable and/or adaptive spike-encoding mechanisms (e.g., gradient-trained or plasticity-based) for temporal and/or spatial information conversion.
A4: Comparison | B4: Conventional or rule-based spike encoders (e.g., rate, latency, phase coding) used in hybrid or pure SNNs.
A5: Outcome | B5: Quantitative results for model performance (e.g., accuracy), computational efficiency (e.g., energy, spike count), training stability, and/or biological plausibility.
A6: Context | B6: Empirical studies conducted using standard neuromorphic datasets (e.g., DVS Gesture, N-MNIST, SHD) and evaluated under both software simulation environments and neuromorphic hardware platforms.
A8: RQs
A9: Purpose | B9: Question Stem
A10: To systematically catalog and characterize the landscape of existing learnable encoding methods, providing a comprehensive taxonomy of approaches and their technical implementations. | B10: RQ1. Findings for RQ1: What learnable or adaptive spike-encoding mechanisms have been proposed in pure SNN or hybrid ANN--SNN architectures?
A11: To quantitatively assess the empirical benefits and trade-offs of learnable encoding methods, determining whether they provide meaningful improvements over traditional approaches. | B11: RQ2. How have these mechanisms influenced model performance, computational efficiency, and training behavior compared with traditional fixed encoding methods?
A12: To identify standardization practices and methodological consistencies (or lack thereof) in the field, revealing community norms and evaluation gaps. | B12: RQ3. What datasets, benchmarks, and evaluation metrics are most commonly used in existing studies?
A13: To synthesize critical challenges and identify promising future research directions that could advance both theoretical understanding and practical applications. | B13: RQ4. What limitations and research gaps remain in developing biologically plausible and energy-efficient encoding strategies?

Sheet search terms
A1: PICOC | B1: Key term | C1: Synonyms / Related Terms
A2: P | B2: Spiking neural network* | C2: "Spiking neural network*" OR "SNN" OR "neuromorphic network*" OR "deep spiking network*" OR "pulsed neural network*" OR "event-driven neural network" OR "event-based spiking network"
A3: P | B3: Hybrid ANN-SNN | C3: "Hybrid ANN-SNN" OR "ANN-SNN conversion" OR "hybrid neural network*" OR "hybrid spiking network*" OR "artificial and spiking neural network*"
A4: I | B4: Learnable encoding | C4: "Learnable encoding" OR "Adaptive encoding" OR "learnable spike encoding" OR "adaptive spike encoding" OR "trainable encoder" OR "differentiable encoding" OR "plastic encoding" OR "adaptive threshold encoding" OR "learnable threshold" OR "surrogate gradient"
A5: I | B5: Adaptive encoding | C5: "Learnable encoding" OR "Adaptive encoding" OR "learnable spike encoding" OR "adaptive spike encoding" OR "trainable encoder" OR "differentiable encoding" OR "plastic encoding" OR "adaptive threshold encoding" OR "learnable threshold" OR "surrogate gradient"
A6: C | B6: Traditional encoding | C6: "TTFS" OR "time-to-first-spike" OR "static" OR "hand-crafted" OR "conventional" OR "rule-based" OR "traditional encoding" OR "rate" OR "temporal encoding" OR "population encoding" OR "direct encoding" OR "latency" OR "fixed threshold" OR "non-adaptive" OR "Poisson"
A7: Ctx | B7: Neuromorphic dataset* | C7: "event-based dataset*" OR "DVS Gesture" OR "N-MNIST" OR "SHD" OR "Spiking Heidelberg Digits" OR "CIFAR-10-DVS" OR "neuromorphic benchmark"
A8: Ctx | B8: Simulation framework* | C8: "software simulation" OR "neuromorphic hardware" OR "Loihi" OR "SpiNNaker" OR "TrueNorth" OR "BindsNET" OR "snnTorch" OR "neuromorphic simulator"

Sheet queries
A1: Query ID | B1: Purpose | C1: Core keywords | D1: Expanded | E1: #tokens
A2: Q1 | B2: To find studies on hybrid ANN–SNN models using learnable or adaptive spike-encoding mechanisms. | C2: "Spiking neural network*" AND "Hybrid ANN-SNN" AND ("Learnable encoding" OR "Adaptive encoding") | D2: ="(" & _xlfn.XLOOKUP("Spiking neural network*",'search terms'!B:B,'search terms'!C:C) & ") AND (" & _xlfn.XLOOKUP("Hybrid ANN-SNN",'search terms'!B:B,'search terms'!C:C) & ") AND (" & _xlfn.XLOOKUP("Learnable encoding",'search terms'!B:B,'search terms'!C:C) & ")" -> ("Spiking neural network*" OR "SNN" OR "neuromorphic network*" OR "deep spiking network*" OR "pulsed neural network*" OR "event-driven neural network" OR "event-based spiking network") AND ("Hybrid ANN-SNN" OR "ANN-SNN conversion" OR "hybrid neural network*" OR "hybrid spiking network*" OR "artificial and spiking neural network*") AND ( "Learnable encoding" OR "Adaptive encoding" OR "learnable spike encoding" OR "adaptive spike encoding" OR "trainable encoder" OR "differentiable encoding" OR "plastic encoding" OR "adaptive threshold encoding" OR "learnable threshold" OR "surrogate gradient") | E2: =ROWS(_xlfn.TEXTSPLIT(D2,," ")) -> 78
A3: Q2 | B3: To identify studies that investigate learnable or adaptive spike-encoding methods, evaluated on event-based or neuromorphic datasets, and compared against traditional encoding approaches. | C3: "Adaptive encoding" AND "Neuromorphic dataset*" AND "Traditional encoding" | D3: ="("&_xlfn.XLOOKUP("Adaptive encoding",'search terms'!B:B,'search terms'!C:C)&") AND ("&_xlfn.XLOOKUP("Neuromorphic dataset*",'search terms'!B:B,'search terms'!C:C) &") AND ("&_xlfn.XLOOKUP("Traditional encoding",'search terms'!B:B,'search terms'!C:C) & ")" -> ( "Learnable encoding" OR "Adaptive encoding" OR "learnable spike encoding" OR "adaptive spike encoding" OR "trainable encoder" OR "differentiable encoding" OR "plastic encoding" OR "adaptive threshold encoding" OR "learnable threshold" OR "surrogate gradient") AND ("event-based dataset*" OR "DVS Gesture" OR "N-MNIST" OR "SHD" OR "Spiking Heidelberg Digits" OR "CIFAR-10-DVS" OR "neuromorphic benchmark") AND ("TTFS" OR "time-to-first-spike" OR "static" OR "hand-crafted" OR "conventional" OR "rule-based" OR "traditional encoding" OR "rate" OR "temporal encoding" OR "population encoding" OR "direct encoding" OR "latency" OR "fixed threshold" OR "non-adaptive" OR "Poisson") | E3: =ROWS(_xlfn.TEXTSPLIT(D3,," ")) -> 87
A4: Q3 | B4: To identify studies that employ adaptive encoding methods on event-based datasets, implemented using neuromorphic hardware or simulation frameworks. | C4: "Neuromorphic dataset*" AND "Simulation framework*" AND "Adaptive encoding" | D4: ="(" & _xlfn.XLOOKUP("Neuromorphic dataset*",'search terms'!B:B,'search terms'!C:C) & ") AND (" & _xlfn.XLOOKUP("Simulation framework*",'search terms'!B:B,'search terms'!C:C) & ") AND (" & _xlfn.XLOOKUP("Adaptive encoding",'search terms'!B:B,'search terms'!C:C) & ")" -> ("event-based dataset*" OR "DVS Gesture" OR "N-MNIST" OR "SHD" OR "Spiking Heidelberg Digits" OR "CIFAR-10-DVS" OR "neuromorphic benchmark") AND ("software simulation" OR "neuromorphic hardware" OR "Loihi" OR "SpiNNaker" OR "TrueNorth" OR "BindsNET" OR "snnTorch" OR "neuromorphic simulator") AND ( "Learnable encoding" OR "Adaptive encoding" OR "learnable spike encoding" OR "adaptive spike encoding" OR "trainable encoder" OR "differentiable encoding" OR "plastic encoding" OR "adaptive threshold encoding" OR "learnable threshold" OR "surrogate gradient") | E4: =ROWS(_xlfn.TEXTSPLIT(D4,," ")) -> 71
A5: Q4 | B5: To identify studies on spiking or neuromorphic neural networks that employ learnable or adaptive spike-encoding techniques, implemented using neuromorphic hardware or simulation frameworks. | C5: ("Learnable encoding" OR "Adaptive encoding") AND "Spiking neural network*" AND "Simulation framework*" | D5: ="(" & _xlfn.XLOOKUP("Learnable encoding",'search terms'!B:B,'search terms'!C:C) & ") AND (" & _xlfn.XLOOKUP( "Spiking neural network*",'search terms'!B:B,'search terms'!C:C) &") AND (" & _xlfn.XLOOKUP( "Simulation framework*",'search terms'!B:B,'search terms'!C:C) &")" -> ( "Learnable encoding" OR "Adaptive encoding" OR "learnable spike encoding" OR "adaptive spike encoding" OR "trainable encoder" OR "differentiable encoding" OR "plastic encoding" OR "adaptive threshold encoding" OR "learnable threshold" OR "surrogate gradient") AND ("Spiking neural network*" OR "SNN" OR "neuromorphic network*" OR "deep spiking network*" OR "pulsed neural network*" OR "event-driven neural network" OR "event-based spiking network") AND ("software simulation" OR "neuromorphic hardware" OR "Loihi" OR "SpiNNaker" OR "TrueNorth" OR "BindsNET" OR "snnTorch" OR "neuromorphic simulator") | E5: =ROWS(_xlfn.TEXTSPLIT(D5,," ")) -> 77
A6: Q5 | B6: To find studies on hybrid ANN–SNN architectures evaluated using event-based or neuromorphic datasets, and compared against traditional encoding approaches. | C6: "Spiking neural network*" AND "Hybrid ANN-SNN" AND "Neuromorphic dataset*" AND "Traditional encoding" | D6: ="(" & _xlfn.XLOOKUP("Spiking neural network*",'search terms'!B:B,'search terms'!C:C) & ") AND (" & _xlfn.XLOOKUP("Hybrid ANN-SNN",'search terms'!B:B,'search terms'!C:C) & ") AND (" & _xlfn.XLOOKUP("Neuromorphic dataset*",'search terms'!B:B,'search terms'!C:C) & ") AND (" & _xlfn.XLOOKUP("Traditional encoding",'search terms'!B:B,'search terms'!C:C) & ")" -> ("Spiking neural network*" OR "SNN" OR "neuromorphic network*" OR "deep spiking network*" OR "pulsed neural network*" OR "event-driven neural network" OR "event-based spiking network") AND ("Hybrid ANN-SNN" OR "ANN-SNN conversion" OR "hybrid neural network*" OR "hybrid spiking network*" OR "artificial and spiking neural network*") AND ("event-based dataset*" OR "DVS Gesture" OR "N-MNIST" OR "SHD" OR "Spiking Heidelberg Digits" OR "CIFAR-10-DVS" OR "neuromorphic benchmark") AND ("TTFS" OR "time-to-first-spike" OR "static" OR "hand-crafted" OR "conventional" OR "rule-based" OR "traditional encoding" OR "rate" OR "temporal encoding" OR "population encoding" OR "direct encoding" OR "latency" OR "fixed threshold" OR "non-adaptive" OR "Poisson") | E6: =ROWS(_xlfn.TEXTSPLIT(D6,," ")) -> 98
A7: Q6 | B7: To locate studies on hybrid ANN–SNN models implemented or tested using neuromorphic hardware or simulation platforms. | C7: "Spiking neural network*" AND "Hybrid ANN-SNN" AND "Simulation framework*" | D7: ="(" & _xlfn.XLOOKUP("Spiking neural network*",'search terms'!B:B,'search terms'!C:C) & ") AND (" & _xlfn.XLOOKUP("Hybrid ANN-SNN",'search terms'!B:B,'search terms'!C:C) & ") AND (" & _xlfn.XLOOKUP("Simulation framework*",'search terms'!B:B,'search terms'!C:C) & ")" -> ("Spiking neural network*" OR "SNN" OR "neuromorphic network*" OR "deep spiking network*" OR "pulsed neural network*" OR "event-driven neural network" OR "event-based spiking network") AND ("Hybrid ANN-SNN" OR "ANN-SNN conversion" OR "hybrid neural network*" OR "hybrid spiking network*" OR "artificial and spiking neural network*") AND ("software simulation" OR "neuromorphic hardware" OR "Loihi" OR "SpiNNaker" OR "TrueNorth" OR "BindsNET" OR "snnTorch" OR "neuromorphic simulator") | E7: =ROWS(_xlfn.TEXTSPLIT(D7,," ")) -> 63
A8: Q7 | B8: To find studies using learnable or adaptive spike-encoding mechanisms. | C8: "Adaptive encoding" AND "Spiking neural network*" | D8: ="(" & _xlfn.XLOOKUP("Spiking neural network*",'search terms'!B:B,'search terms'!C:C) & ") AND (" & _xlfn.XLOOKUP("Adaptive encoding",'search terms'!B:B,'search terms'!C:C) & ")" -> ("Spiking neural network*" OR "SNN" OR "neuromorphic network*" OR "deep spiking network*" OR "pulsed neural network*" OR "event-driven neural network" OR "event-based spiking network") AND ( "Learnable encoding" OR "Adaptive encoding" OR "learnable spike encoding" OR "adaptive spike encoding" OR "trainable encoder" OR "differentiable encoding" OR "plastic encoding" OR "adaptive threshold encoding" OR "learnable threshold" OR "surrogate gradient") | E8: =ROWS(_xlfn.TEXTSPLIT(D8,," ")) -> 58

Sheet databases
A1: No. | B1: Database | C1: Abbreviation
A2: D1 | B2: IEEE Xplore | C2: ieee
A3: D2 | B3: ACM Digital Library | C3: acm
A4: D3 | B4: Scopus | C4: scopus
A5: D5 | B5: ScienceDirect | C5: scidir
A6: D6 | B6: SpringerLink | C6: springer
A7: D7 | B7: arXiv.org | C7: arxiv

Sheet search hits
A1: Database | B1: Query ID | C1: Query String | D1: Hits | E1: Date | F1: Notes | G1: File Path | H1: Name
A2: IEEE Xplore | B2: Q1 | C2: ("Full Text & Metadata":"Spiking neural network*" OR "Full Text & Metadata":"SNN" OR "Full Text & Metadata":"neuromorphic network*" OR "Full Text & Metadata":"deep spiking network*" OR "Full Text & Metadata":"pulsed neural network*" OR "Full Text & Metadata":"event-driven neural network" OR "Full Text & Metadata":"event-based spiking network") AND ("Full Text & Metadata":"Hybrid ANN-SNN" OR "Full Text & Metadata":"ANN-SNN conversion" OR "Full Text & Metadata":"hybrid neural network*" OR "Full Text & Metadata":"hybrid spiking network*" OR "Full Text & Metadata":"artificial and spiking neural network*") AND ("Full Text & Metadata":"Learnable encoding" OR "Full Text & Metadata":"Adaptive encoding" OR "Full Text & Metadata":"learnable spike encoding" OR "Full Text & Metadata":"adaptive spike encoding" OR "Full Text & Metadata":"trainable encoder" OR "Full Text & Metadata":"differentiable encoding" OR "Full Text & Metadata":"plastic encoding" OR "Full Text & Metadata":"adaptive threshold encoding" OR "Full Text & Metadata":"learnable threshold" OR "Full Text & Metadata":"surrogate gradient") | D2: 13 | E2: 45968 | F2: Advanced search (Full Text & Metadata); Filters Applied: Journals + Early Access+ open access only+ Articles 01/01/2015 - 11/07/2025 | G2: "D:\MyMasterDegreeJourney\Second year\Semester 1\Graduation research\Research logs\Q1" | H2: ieee_q1.bib
A3: ACM Digital Library | B3: Q1 | C3: =_xlfn.XLOOKUP("Q1",queries!A2, queries!D2) -> ("Spiking neural network*" OR "SNN" OR "neuromorphic network*" OR "deep spiking network*" OR "pulsed neural network*" OR "event-driven neural network" OR "event-based spiking network") AND ("Hybrid ANN-SNN" OR "ANN-SNN conversion" OR "hybrid neural network*" OR "hybrid spiking network*" OR "artificial and spiking neural network*") AND ( "Learnable encoding" OR "Adaptive encoding" OR "learnable spike encoding" OR "adaptive spike encoding" OR "trainable encoder" OR "differentiable encoding" OR "plastic encoding" OR "adaptive threshold encoding" OR "learnable threshold" OR "surrogate gradient") | D3: 18 | E3: 45968 | F3: Advanced Search: Search within anywhere; Custom Range (jan-2015; Nov-2025) | G3: "D:\MyMasterDegreeJourney\Second year\Semester 1\Graduation research\Research logs\Q1" | H3: acm_q1.bib
A4: Scopus | B4: Q1 | C4: =_xlfn.XLOOKUP("Q1",queries!A2, queries!D2) -> ("Spiking neural network*" OR "SNN" OR "neuromorphic network*" OR "deep spiking network*" OR "pulsed neural network*" OR "event-driven neural network" OR "event-based spiking network") AND ("Hybrid ANN-SNN" OR "ANN-SNN conversion" OR "hybrid neural network*" OR "hybrid spiking network*" OR "artificial and spiking neural network*") AND ( "Learnable encoding" OR "Adaptive encoding" OR "learnable spike encoding" OR "adaptive spike encoding" OR "trainable encoder" OR "differentiable encoding" OR "plastic encoding" OR "adaptive threshold encoding" OR "learnable threshold" OR "surrogate gradient") | D4: 25 | E4: 45967 | F4: Q1 searched across three fields: (1) All fields – spiking or neuromorphic neural network terms, (2) All fields – hybrid ANN–SNN or conversion terms, and (3) Article title, Abstract, Keywords – learnable/adaptive encoding terms. Filter: Open Access; (2015-2025,English) | G4: "D:\MyMasterDegreeJourney\Second year\Semester 1\Graduation research\Research logs\Q1" | H4: scopus_q1.bib
A5: ScienceDirect | B5: Q1 | C5: ( "Learnable encoding" OR "Adaptive encoding" OR "learnable spike encoding" OR "adaptive spike encoding" OR "trainable encoder" OR "differentiable encoding" OR "adaptive threshold encoding" OR "learnable threshold" OR "surrogate gradient") ("Spiking neural network" OR "SNN" OR "neuromorphic network" OR "deep spiking network" OR "pulsed neural network" OR "event-driven neural network" OR "event-based spiking network") ("Hybrid ANN-SNN" OR "ANN-SNN conversion" OR "hybrid neural network" OR "hybrid spiking network" OR "artificial and spiking neural network") | D5: 2 | E5: 45967 | F5: Q1 searched across three fields: (1) All fields – learnable/adaptive encoding terms, (2) Title/Abstract/Keywords – SNN-related terms, and (3) Title – hybrid ANN–SNN terms. Open Access filter not applide; so all 2 not open access. | G5: "D:\MyMasterDegreeJourney\Second year\Semester 1\Graduation research\Research logs\Q1" | H5: scidir_q1.bib
A6: SpringerLink | B6: Q1 | C6: =_xlfn.XLOOKUP("Q1",queries!A2, queries!D2) -> ("Spiking neural network*" OR "SNN" OR "neuromorphic network*" OR "deep spiking network*" OR "pulsed neural network*" OR "event-driven neural network" OR "event-based spiking network") AND ("Hybrid ANN-SNN" OR "ANN-SNN conversion" OR "hybrid neural network*" OR "hybrid spiking network*" OR "artificial and spiking neural network*") AND ( "Learnable encoding" OR "Adaptive encoding" OR "learnable spike encoding" OR "adaptive spike encoding" OR "trainable encoder" OR "differentiable encoding" OR "plastic encoding" OR "adaptive threshold encoding" OR "learnable threshold" OR "surrogate gradient") | D6: 11 | E6: 45967 | F6: advanced search across all fields (title, abstract, keywords, and full text); Filters: custom dates (2015-2025); English; Open access | G6: "D:\MyMasterDegreeJourney\Second year\Semester 1\Graduation research\Research logs\Q1" | H6: springer_q1.bib
A7: arXiv.org | B7: Q1 | C7: =_xlfn.XLOOKUP("Q1",queries!A2, queries!D2) -> ("Spiking neural network*" OR "SNN" OR "neuromorphic network*" OR "deep spiking network*" OR "pulsed neural network*" OR "event-driven neural network" OR "event-based spiking network") AND ("Hybrid ANN-SNN" OR "ANN-SNN conversion" OR "hybrid neural network*" OR "hybrid spiking network*" OR "artificial and spiking neural network*") AND ( "Learnable encoding" OR "Adaptive encoding" OR "learnable spike encoding" OR "adaptive spike encoding" OR "trainable encoder" OR "differentiable encoding" OR "plastic encoding" OR "adaptive threshold encoding" OR "learnable threshold" OR "surrogate gradient") | D7: 5 | E7: 45967 | F7: advanced search across all fields (title, abstract, keywords, and full text); custom dates (2015-2025) | G7: "D:\MyMasterDegreeJourney\Second year\Semester 1\Graduation research\Research logs\Q1" | H7: acm_q1.bib
A8: IEEE Xplore | B8: Q2 | C8: ("Full Text & Metadata":"Learnable encoding" OR "Full Text & Metadata":"Adaptive encoding" OR "Full Text & Metadata":"learnable spike encoding" OR "Full Text & Metadata":"adaptive spike encoding" OR "Full Text & Metadata":"trainable encoder" OR "Full Text & Metadata":"differentiable encoding" OR "Full Text & Metadata":"plastic encoding" OR "Full Text & Metadata":"adaptive threshold encoding" OR "Full Text & Metadata":"learnable threshold" OR "Full Text & Metadata":"surrogate gradient") AND ("Full Text & Metadata":"event-based dataset*" OR "Full Text & Metadata":"DVS Gesture" OR "Full Text & Metadata":"N-MNIST" OR "Full Text & Metadata":"SHD" OR "Full Text & Metadata":"Spiking Heidelberg Digits" OR "Full Text & Metadata":"CIFAR-10-DVS" OR "Full Text & Metadata":"neuromorphic benchmark") AND ("Full Text & Metadata":"TTFS" OR "Full Text & Metadata":"time-to-first-spike" OR "Full Text & Metadata":"static" OR "Full Text & Metadata":"hand-crafted" OR "Full Text & Metadata":"conventional" OR "Full Text & Metadata":"rule-based" OR "Full Text & Metadata":"traditional encoding" OR "Full Text & Metadata":"rate" OR "Full Text & Metadata":"temporal encoding" OR "Full Text & Metadata":"population encoding" OR "Full Text & Metadata":"direct encoding" OR "Full Text & Metadata":"latency" OR "Full Text & Metadata":"fixed threshold" OR "Full Text & Metadata":"non-adaptive" OR "Full Text & Metadata":"Poisson") | D8: 18 | E8: 45967 | F8: Advanced search (Full Text & Metadata); Filters Applied: Journals + Early Access+ open access only+ Articles 01/01/2015 - 11/07/2025 | G8: "D:\MyMasterDegreeJourney\Second year\Semester 1\Graduation research\Research logs\Q2" | H8: ieee_q2.bib
A9: ACM Digital Library | B9: Q2 | C9: =_xlfn.XLOOKUP("Q2",queries!A3, queries!D3) -> ( "Learnable encoding" OR "Adaptive encoding" OR "learnable spike encoding" OR "adaptive spike encoding" OR "trainable encoder" OR "differentiable encoding" OR "plastic encoding" OR "adaptive threshold encoding" OR "learnable threshold" OR "surrogate gradient") AND ("event-based dataset*" OR "DVS Gesture" OR "N-MNIST" OR "SHD" OR "Spiking Heidelberg Digits" OR "CIFAR-10-DVS" OR "neuromorphic benchmark") AND ("TTFS" OR "time-to-first-spike" OR "static" OR "hand-crafted" OR "conventional" OR "rule-based" OR "traditional encoding" OR "rate" OR "temporal encoding" OR "population encoding" OR "direct encoding" OR "latency" OR "fixed threshold" OR "non-adaptive" OR "Poisson") | D9: 17 | E9: 45967 | F9: Advanced Search: Search within anywhere; filters: Proceedings, Research Article, January 2015 - November 2025 | G9: "D:\MyMasterDegreeJourney\Second year\Semester 1\Graduation research\Research logs\Q2" | H9: acm_q2.bib
A10: Scopus | B10: Q2 | C10: TITLE-ABS-KEY ( ( "Learnable encoding" OR "Adaptive encoding" OR "learnable spike encoding" OR "adaptive spike encoding" OR "trainable encoder" OR "differentiable encoding" OR "plastic encoding" OR "adaptive threshold encoding" OR "learnable threshold" OR "surrogate gradient" ) AND ( "event-based dataset*" OR "DVS Gesture" OR "N-MNIST" OR "SHD" OR "Spiking Heidelberg Digits" OR "CIFAR-10-DVS" OR "neuromorphic benchmark" ) AND ( "TTFS" OR "time-to-first-spike" OR "static" OR "hand-crafted" OR "conventional" OR "rule-based" OR "traditional encoding" OR "rate" OR "temporal encoding" OR "population encoding" OR "direct encoding" OR "latency" OR "fixed threshold" OR "non-adaptive" OR "Poisson" ) ) AND PUBYEAR > 2014 AND PUBYEAR < 2025 AND ( LIMIT-TO ( OA , "all" ) OR LIMIT-TO ( OA , "publisherfullgold" ) OR LIMIT-TO ( OA , "repository" ) ) AND ( LIMIT-TO ( LANGUAGE , "English" ) ) | D10: 4 | E10: 45967 | F10: Advanced search (TITLE-ABS-KEY); filter applied: limited to English, All open access => includes Gold, Green, Hybrid gold | G10: "D:\MyMasterDegreeJourney\Second year\Semester 1\Graduation research\Research logs\Q2" | H10: scopus_q2.bib
A11: ScienceDirect | B11: Q2 | C11: ( "Learnable encoding" OR "Adaptive encoding" OR "learnable spike encoding" OR "adaptive spike encoding" OR "trainable encoder" OR "differentiable encoding" OR "adaptive threshold encoding" OR "learnable threshold" OR "surrogate gradient") ("event-based dataset" OR "DVS Gesture" OR "N-MNIST" OR "SHD" OR "Spiking Heidelberg Digits" OR "CIFAR-10-DVS") AND ("TTFS" OR "time-to-first-spike" OR "static" ) | D11: 2 | E11: 45967 | F11: Q2 searched using two sub-queries: (1) Title/Abstract/Keywords – learnable/adaptive encoding terms, and (2) All Fields – event-based dataset and temporal-encoding terms (e.g., TTFS, static). Filter: Open Access. | G11: "D:\MyMasterDegreeJourney\Second year\Semester 1\Graduation research\Research logs\Q2" | H11: scidir_q2.bib
A12: SpringerLink | B12: Q2 | C12: =_xlfn.XLOOKUP("Q2",queries!A3, queries!D3) -> ( "Learnable encoding" OR "Adaptive encoding" OR "learnable spike encoding" OR "adaptive spike encoding" OR "trainable encoder" OR "differentiable encoding" OR "plastic encoding" OR "adaptive threshold encoding" OR "learnable threshold" OR "surrogate gradient") AND ("event-based dataset*" OR "DVS Gesture" OR "N-MNIST" OR "SHD" OR "Spiking Heidelberg Digits" OR "CIFAR-10-DVS" OR "neuromorphic benchmark") AND ("TTFS" OR "time-to-first-spike" OR "static" OR "hand-crafted" OR "conventional" OR "rule-based" OR "traditional encoding" OR "rate" OR "temporal encoding" OR "population encoding" OR "direct encoding" OR "latency" OR "fixed threshold" OR "non-adaptive" OR "Poisson") | D12: 15 | E12: 45967 | F12: advanced search across all fields (title, abstract, keywords, and full text); limited to publications written in English, published between 2015 and 2025, and classified as Articles, Research Articles, Conference Papers, or Review Articles. The Open Access filter was also applied to ensure accessibility. | G12: "D:\MyMasterDegreeJourney\Second year\Semester 1\Graduation research\Research logs\Q2" | H12: springer_q2.bib
A13: arXiv.org | B13: Q2 | C13: =_xlfn.XLOOKUP("Q2",queries!A3, queries!D3) -> ( "Learnable encoding" OR "Adaptive encoding" OR "learnable spike encoding" OR "adaptive spike encoding" OR "trainable encoder" OR "differentiable encoding" OR "plastic encoding" OR "adaptive threshold encoding" OR "learnable threshold" OR "surrogate gradient") AND ("event-based dataset*" OR "DVS Gesture" OR "N-MNIST" OR "SHD" OR "Spiking Heidelberg Digits" OR "CIFAR-10-DVS" OR "neuromorphic benchmark") AND ("TTFS" OR "time-to-first-spike" OR "static" OR "hand-crafted" OR "conventional" OR "rule-based" OR "traditional encoding" OR "rate" OR "temporal encoding" OR "population encoding" OR "direct encoding" OR "latency" OR "fixed threshold" OR "non-adaptive" OR "Poisson") | D13: 5 | E13: 45967 | F13: advanced search across all fields (title, abstract, keywords, and full text); custom dates (2015-2025) | G13: "D:\MyMasterDegreeJourney\Second year\Semester 1\Graduation research\Research logs\Q2" | H13: arxiv_q2.bib
A14: IEEE Xplore | B14: Q3 | C14: ("Full Text & Metadata":"event-based dataset*" OR "Full Text & Metadata":"DVS Gesture" OR "Full Text & Metadata":"N-MNIST" OR "Full Text & Metadata":"SHD" OR "Full Text & Metadata":"Spiking Heidelberg Digits" OR "Full Text & Metadata":"CIFAR-10-DVS" OR "Full Text & Metadata":"neuromorphic benchmark") AND ("Full Text & Metadata":"software simulation" OR "Full Text & Metadata":"neuromorphic hardware" OR "Full Text & Metadata":"Loihi" OR "Full Text & Metadata":"SpiNNaker" OR "Full Text & Metadata":"TrueNorth" OR "Full Text & Metadata":"BindsNET" OR "Full Text & Metadata":"snnTorch" OR "Full Text & Metadata":"neuromorphic simulator") AND ("Full Text & Metadata":"Learnable encoding" OR "Full Text & Metadata":"Adaptive encoding" OR "Full Text & Metadata":"learnable spike encoding" OR "Full Text & Metadata":"adaptive spike encoding" OR "Full Text & Metadata":"trainable encoder" OR "Full Text & Metadata":"differentiable encoding" OR "Full Text & Metadata":"plastic encoding" OR "Full Text & Metadata":"adaptive threshold encoding" OR "Full Text & Metadata":"learnable threshold" OR "Full Text & Metadata":"surrogate gradient") | D14: 15 | E14: 45967 | F14: Advanced search (Full Text & Metadata); Filters Applied: Journals + Early Access+ open access only+ Articles 01/01/2015 - 11/07/2025 | G14: "D:\MyMasterDegreeJourney\Second year\Semester 1\Graduation research\Research logs\Q3" | H14: ieee_q3.bib
A15: ACM Digital Library | B15: Q3 | C15: =_xlfn.XLOOKUP("Q3",queries!A4, queries!D4) -> ("event-based dataset*" OR "DVS Gesture" OR "N-MNIST" OR "SHD" OR "Spiking Heidelberg Digits" OR "CIFAR-10-DVS" OR "neuromorphic benchmark") AND ("software simulation" OR "neuromorphic hardware" OR "Loihi" OR "SpiNNaker" OR "TrueNorth" OR "BindsNET" OR "snnTorch" OR "neuromorphic simulator") AND ( "Learnable encoding" OR "Adaptive encoding" OR "learnable spike encoding" OR "adaptive spike encoding" OR "trainable encoder" OR "differentiable encoding" OR "plastic encoding" OR "adaptive threshold encoding" OR "learnable threshold" OR "surrogate gradient") | D15: 22 | E15: 45967 | F15: Advanced search (Full Text & Metadata); Filters Applied: Journals + Early Access+ open access only+ Articles 01/01/2015 - 11/07/2025 | G15: "D:\MyMasterDegreeJourney\Second year\Semester 1\Graduation research\Research logs\Q3" | H15: acm_q3.bib
A16: Scopus | B16: Q3 | C16: TITLE-ABS-KEY ( ( "event-based dataset*" OR "DVS Gesture" OR "N-MNIST" OR "SHD" OR "Spiking Heidelberg Digits" OR "CIFAR-10-DVS" OR "neuromorphic benchmark" ) AND ( "software simulation" OR "neuromorphic hardware" OR "Loihi" OR "SpiNNaker" OR "TrueNorth" OR "BindsNET" OR "snnTorch" OR "neuromorphic simulator" ) AND ( "Learnable encoding" OR "Adaptive encoding" OR "learnable spike encoding" OR "adaptive spike encoding" OR "trainable encoder" OR "differentiable encoding" OR "plastic encoding" OR "adaptive threshold encoding" OR "learnable threshold" OR "surrogate gradient" ) ) AND PUBYEAR > 2019 AND PUBYEAR < 2026 AND ( LIMIT-TO ( LANGUAGE , "English" ) ) AND ( LIMIT-TO ( OA , "all" ) OR LIMIT-TO ( OA , "repository" ) OR LIMIT-TO ( OA , "publisherfullgold" ) ) | D16: 3 | E16: 45967 | F16: Advanced search (TITLE-ABS-KEY); filter applied: limited to English, All open access => includes Gold, Green, Hybrid gold | G16: "D:\MyMasterDegreeJourney\Second year\Semester 1\Graduation research\Research logs\Q3" | H16: scopus_q3.bib
A17: ScienceDirect | B17: Q3 | C17: "Learnable encoding" OR "Adaptive encoding" OR "learnable spike encoding" OR "adaptive spike encoding" OR "trainable encoder" OR "differentiable encoding" OR "adaptive threshold encoding" OR "learnable threshold" OR "surrogate gradient" "event-based dataset" OR "DVS Gesture" OR "N-MNIST" OR "SHD" OR "Spiking Heidelberg Digits" OR "CIFAR-10-DVS" OR "neuromorphic benchmark" OR "software simulation" OR "neuromorphic hardware" | D17: 11 | E17: 45967 | F17: Q3 searched across two fields: (1) All Fields – learnable/adaptive encoding terms, and (2) Title/Abstract/Keywords – event-based dataset and neuromorphic system terms (e.g., software simulation, hardware). Filter: Open Access. | G17: "D:\MyMasterDegreeJourney\Second year\Semester 1\Graduation research\Research logs\Q3" | H17: scidir_q3.bib
A18: SpringerLink | B18: Q3 | C18: =_xlfn.XLOOKUP("Q3",queries!A4, queries!D4) -> ("event-based dataset*" OR "DVS Gesture" OR "N-MNIST" OR "SHD" OR "Spiking Heidelberg Digits" OR "CIFAR-10-DVS" OR "neuromorphic benchmark") AND ("software simulation" OR "neuromorphic hardware" OR "Loihi" OR "SpiNNaker" OR "TrueNorth" OR "BindsNET" OR "snnTorch" OR "neuromorphic simulator") AND ( "Learnable encoding" OR "Adaptive encoding" OR "learnable spike encoding" OR "adaptive spike encoding" OR "trainable encoder" OR "differentiable encoding" OR "plastic encoding" OR "adaptive threshold encoding" OR "learnable threshold" OR "surrogate gradient") | D18: 12 | E18: 45967 | F18: advanced search across all fields (title, abstract, keywords, and full text); limited to publications written in English, published between 2015 and 2025, and classified as Articles, Research Articles, Conference Papers, or Review Articles. The Open Access filter was also applied to ensure accessibility. | G18: "D:\MyMasterDegreeJourney\Second year\Semester 1\Graduation research\Research logs\Q3" | H18: springer_q3.bib
A19: arXiv.org | B19: Q3 | C19: =_xlfn.XLOOKUP("Q3",queries!A4, queries!D4) -> ("event-based dataset*" OR "DVS Gesture" OR "N-MNIST" OR "SHD" OR "Spiking Heidelberg Digits" OR "CIFAR-10-DVS" OR "neuromorphic benchmark") AND ("software simulation" OR "neuromorphic hardware" OR "Loihi" OR "SpiNNaker" OR "TrueNorth" OR "BindsNET" OR "snnTorch" OR "neuromorphic simulator") AND ( "Learnable encoding" OR "Adaptive encoding" OR "learnable spike encoding" OR "adaptive spike encoding" OR "trainable encoder" OR "differentiable encoding" OR "plastic encoding" OR "adaptive threshold encoding" OR "learnable threshold" OR "surrogate gradient") | D19: 2 | E19: 45967 | F19: advanced search across all fields (title, abstract, keywords, and full text); custom dates (2015-2025) | G19: "D:\MyMasterDegreeJourney\Second year\Semester 1\Graduation research\Research logs\Q3" | H19: arxiv_q3.bib
A20: IEEE Xplore | B20: Q4 | C20: ("All Metadata":"Learnable encoding" OR "All Metadata":"Adaptive encoding" OR "All Metadata":"learnable spike encoding" OR "All Metadata":"adaptive spike encoding" OR "All Metadata":"trainable encoder" OR "All Metadata":"differentiable encoding" OR "All Metadata":"plastic encoding" OR "All Metadata":"adaptive threshold encoding" OR "All Metadata":"learnable threshold" OR "All Metadata":"surrogate gradient") AND ("All Metadata":"Spiking neural network*" OR "All Metadata":"SNN" OR "All Metadata":"neuromorphic network*" OR "All Metadata":"deep spiking network*" OR "All Metadata":"pulsed neural network*" OR "All Metadata":"event-driven neural network" OR "All Metadata":"event-based spiking network") AND ("All Metadata":"software simulation" OR "All Metadata":"neuromorphic hardware" OR "All Metadata":"Loihi" OR "All Metadata":"SpiNNaker" OR "All Metadata":"TrueNorth" OR "All Metadata":"BindsNET" OR "All Metadata":"snnTorch" OR "All Metadata":"neuromorphic simulator") | D20: 2 | E20: 45967 | F20: Advanced search (ALL Metadata); Filters Applied: Journals + open access only + Articles 01/01/2015 - 11/07/2025 | G20: "D:\MyMasterDegreeJourney\Second year\Semester 1\Graduation research\Research logs\Q4" | H20: ieee_q4.bib
A21: ACM Digital Library | B21: Q4 | C21: =_xlfn.XLOOKUP("Q4",queries!A5, queries!D5) -> ( "Learnable encoding" OR "Adaptive encoding" OR "learnable spike encoding" OR "adaptive spike encoding" OR "trainable encoder" OR "differentiable encoding" OR "plastic encoding" OR "adaptive threshold encoding" OR "learnable threshold" OR "surrogate gradient") AND ("Spiking neural network*" OR "SNN" OR "neuromorphic network*" OR "deep spiking network*" OR "pulsed neural network*" OR "event-driven neural network" OR "event-based spiking network") AND ("software simulation" OR "neuromorphic hardware" OR "Loihi" OR "SpiNNaker" OR "TrueNorth" OR "BindsNET" OR "snnTorch" OR "neuromorphic simulator") | D21: 16 | E21: 45967 | F21: Searched for learnable/adaptive encoding terms in All Fields, combined with spiking neural network and hardware/simulation terms searched in the Abstract. Filter: publication years 2015–2025 | G21: "D:\MyMasterDegreeJourney\Second year\Semester 1\Graduation research\Research logs\Q4" | H21: acm_q4.bib
A22: Scopus | B22: Q4 | C22: TITLE-ABS-KEY ( ( "Learnable encoding" OR "Adaptive encoding" OR "learnable spike encoding" OR "adaptive spike encoding" OR "trainable encoder" OR "differentiable encoding" OR "plastic encoding" OR "adaptive threshold encoding" OR "learnable threshold" OR "surrogate gradient" ) AND ( "Spiking neural network*" OR "SNN" OR "neuromorphic network*" OR "deep spiking network*" OR "pulsed neural network*" OR "event-driven neural network" OR "event-based spiking network" ) AND ( "software simulation" OR "neuromorphic hardware" OR "Loihi" OR "SpiNNaker" OR "TrueNorth" OR "BindsNET" OR "snnTorch" OR "neuromorphic simulator" ) ) AND PUBYEAR > 2014 AND PUBYEAR < 2026 AND PUBYEAR > 2019 AND PUBYEAR < 2026 AND ( LIMIT-TO ( OA , "all" ) OR LIMIT-TO ( OA , "publisherfullgold" ) OR LIMIT-TO ( OA , "publisherhybridgold" ) OR LIMIT-TO ( OA , "repository" ) ) AND ( LIMIT-TO ( DOCTYPE , "ar" ) OR LIMIT-TO ( DOCTYPE , "cp" ) OR LIMIT-TO ( DOCTYPE , "re" ) ) AND ( LIMIT-TO ( LANGUAGE , "English" ) ) | D22: 22 | E22: 45967 | F22: Queried TITLE-ABS-KEY for three concept blocks — (learnable/adaptive encoding terms) AND (spiking/neuromorphic network terms) AND (software simulation / neuromorphic hardware & tools: Loihi, SpiNNaker, TrueNorth, BindsNET, snnTorch, etc.). Years: 2020–2025 (PUBYEAR > 2019 & < 2026). Access: Open Access only (all OA types: publisher full gold, repository/green, hybrid gold). Language: English. Document types: Article (ar), Conference Paper (cp), Review (re). | G22: "D:\MyMasterDegreeJourney\Second year\Semester 1\Graduation research\Research logs\Q4" | H22: scopus_q4.bib
A23: ScienceDirect | B23: Q4 | C23: ("Learnable encoding" OR "Adaptive encoding" OR "learnable spike encoding" OR "adaptive spike encoding" OR "trainable encoder" OR "differentiable encoding" OR "adaptive threshold encoding" OR "learnable threshold" OR "surrogate gradient") ("software simulation" OR "neuromorphic hardware" OR "Loihi" OR "SpiNNaker" OR "TrueNorth" OR "BindsNET" OR "snnTorch" OR "neuromorphic simulator") ("Spiking neural network" OR "SNN" OR "neuromorphic network" OR "deep spiking network" OR "pulsed neural network" OR "event-driven neural network") | D23: 3 | E23: 45967 | F23: Q4 searched across 3 fields: (1) All Fields – learnable/adaptive encoding term; and (2) on Title/Abstract/Keywords software simulation terms ; and (3) searched in Title only: Spiking neural network terms, Filter: Open Access. (2015,2025) | G23: "D:\MyMasterDegreeJourney\Second year\Semester 1\Graduation research\Research logs\Q4" | H23: scidir_q4.bib
A24: SpringerLink | B24: Q4 | C24: =_xlfn.XLOOKUP("Q4",queries!A5, queries!D5) -> ( "Learnable encoding" OR "Adaptive encoding" OR "learnable spike encoding" OR "adaptive spike encoding" OR "trainable encoder" OR "differentiable encoding" OR "plastic encoding" OR "adaptive threshold encoding" OR "learnable threshold" OR "surrogate gradient") AND ("Spiking neural network*" OR "SNN" OR "neuromorphic network*" OR "deep spiking network*" OR "pulsed neural network*" OR "event-driven neural network" OR "event-based spiking network") AND ("software simulation" OR "neuromorphic hardware" OR "Loihi" OR "SpiNNaker" OR "TrueNorth" OR "BindsNET" OR "snnTorch" OR "neuromorphic simulator") | D24: 36 | E24: 45967 | F24: Q4: Queried All Fields; Document type – Article, Research article, Review article; Publication year – 2015 to 2025; Language – English; Access type – Open Access only. | G24: "D:\MyMasterDegreeJourney\Second year\Semester 1\Graduation research\Research logs\Q4" | H24: springer_q4.bib
A25: arXiv.org | B25: Q4 | C25: =_xlfn.XLOOKUP("Q4",queries!A5, queries!D5) -> ( "Learnable encoding" OR "Adaptive encoding" OR "learnable spike encoding" OR "adaptive spike encoding" OR "trainable encoder" OR "differentiable encoding" OR "plastic encoding" OR "adaptive threshold encoding" OR "learnable threshold" OR "surrogate gradient") AND ("Spiking neural network*" OR "SNN" OR "neuromorphic network*" OR "deep spiking network*" OR "pulsed neural network*" OR "event-driven neural network" OR "event-based spiking network") AND ("software simulation" OR "neuromorphic hardware" OR "Loihi" OR "SpiNNaker" OR "TrueNorth" OR "BindsNET" OR "snnTorch" OR "neuromorphic simulator") | D25: 26 | E25: 45967 | F25: Queried the Abstract field only; (2015-2025) | G25: "D:\MyMasterDegreeJourney\Second year\Semester 1\Graduation research\Research logs\Q4" | H25: arxiv_q4.bib
A26: IEEE Xplore | B26: Q5 | C26: ("Full Text & Metadata":("Spiking neural network*" OR "Full Text & Metadata":"SNN" OR "Full Text & Metadata":"neuromorphic network*" OR "Full Text & Metadata":"deep spiking network*" OR "Full Text & Metadata":"pulsed neural network*" OR "Full Text & Metadata":"event-driven neural network" OR "Full Text & Metadata":"event-based spiking network")) AND ("Full Text & Metadata":("Hybrid ANN-SNN" OR "Full Text & Metadata":"ANN-SNN conversion" OR "Full Text & Metadata":"hybrid neural network*" OR "Full Text & Metadata":"hybrid spiking network*" OR "Full Text & Metadata":"artificial and spiking neural network*")) AND ("Full Text & Metadata":("event-based dataset*" OR "Full Text & Metadata":"DVS Gesture" OR "Full Text & Metadata":"N-MNIST" OR "Full Text & Metadata":"SHD" OR "Full Text & Metadata":"Spiking Heidelberg Digits" OR "Full Text & Metadata":"CIFAR-10-DVS" OR "Full Text & Metadata":"neuromorphic benchmark")) AND ("Full Text & Metadata":("TTFS" OR "Full Text & Metadata":"time-to-first-spike" OR "Full Text & Metadata":"static" OR "Full Text & Metadata":"hand-crafted" OR "Full Text & Metadata":"conventional" OR "Full Text & Metadata":"rule-based" OR "Full Text & Metadata":"traditional encoding" OR "Full Text & Metadata":"rate" OR "Full Text & Metadata":"temporal encoding" OR "Full Text & Metadata":"population encoding" OR "Full Text & Metadata":"direct encoding" OR "Full Text & Metadata":"latency" OR "Full Text & Metadata":"fixed threshold" OR "Full Text & Metadata":"non-adaptive" OR "Full Text & Metadata":"Poisson")) | D26: 0 | E26: 45967 | F26: Queried the Full Text & Metadata field for four concept groups: Spiking, Hybrid architectures ,Datasets , traditnal encoding Field searched: Full Text & Metadata (broad coverage including title, abstract, and indexed metadata). Filters: none applied for year, access type, or language at query stage. | G26: "D:\MyMasterDegreeJourney\Second year\Semester 1\Graduation research\Research logs\Q5" | H26: ieee_q5.bib
A27: ACM Digital Library | B27: Q5 | C27: =_xlfn.XLOOKUP("Q5",queries!A6, queries!D6) -> ("Spiking neural network*" OR "SNN" OR "neuromorphic network*" OR "deep spiking network*" OR "pulsed neural network*" OR "event-driven neural network" OR "event-based spiking network") AND ("Hybrid ANN-SNN" OR "ANN-SNN conversion" OR "hybrid neural network*" OR "hybrid spiking network*" OR "artificial and spiking neural network*") AND ("event-based dataset*" OR "DVS Gesture" OR "N-MNIST" OR "SHD" OR "Spiking Heidelberg Digits" OR "CIFAR-10-DVS" OR "neuromorphic benchmark") AND ("TTFS" OR "time-to-first-spike" OR "static" OR "hand-crafted" OR "conventional" OR "rule-based" OR "traditional encoding" OR "rate" OR "temporal encoding" OR "population encoding" OR "direct encoding" OR "latency" OR "fixed threshold" OR "non-adaptive" OR "Poisson") | D27: 11 | E27: 45967 | F27: Field searched: All Fields (includes title, abstract, and metadata). Filters: (2015-2025) | G27: "D:\MyMasterDegreeJourney\Second year\Semester 1\Graduation research\Research logs\Q5" | H27: acm_q5.bib
A28: Scopus | B28: Q5 | C28: =_xlfn.XLOOKUP("Q5",queries!A6, queries!D6) -> ("Spiking neural network*" OR "SNN" OR "neuromorphic network*" OR "deep spiking network*" OR "pulsed neural network*" OR "event-driven neural network" OR "event-based spiking network") AND ("Hybrid ANN-SNN" OR "ANN-SNN conversion" OR "hybrid neural network*" OR "hybrid spiking network*" OR "artificial and spiking neural network*") AND ("event-based dataset*" OR "DVS Gesture" OR "N-MNIST" OR "SHD" OR "Spiking Heidelberg Digits" OR "CIFAR-10-DVS" OR "neuromorphic benchmark") AND ("TTFS" OR "time-to-first-spike" OR "static" OR "hand-crafted" OR "conventional" OR "rule-based" OR "traditional encoding" OR "rate" OR "temporal encoding" OR "population encoding" OR "direct encoding" OR "latency" OR "fixed threshold" OR "non-adaptive" OR "Poisson") | D28: 22 | E28: 45967 | F28: Field searched: All Fields (includes title, abstract, and metadata), (2015-2025), open access, english | G28: "D:\MyMasterDegreeJourney\Second year\Semester 1\Graduation research\Research logs\Q5" | H28: scopus_q5.bib
A29: ScienceDirect | B29: Q5 | C29: Spiking neural network OR "SNN" OR "neuromorphic network" OR "deep spiking network" OR "pulsed neural network" OR "event-driven neural network" OR "event-based spiking network" AND ("event-based dataset" OR "neuromorphic benchmark" ) "TTFS" OR "time-to-first-spike" OR "traditional encoding" OR "rate" OR "temporal encoding" OR "population encoding" OR "fixed threshold" OR "non-adaptive" OR "Poisson" ("Hybrid ANN-SNN" OR "ANN-SNN conversion" OR "hybrid neural network" OR "hybrid spiking network" OR "artificial and spiking neural network") | D29: 1 | E29: 45967 | F29: Q5: 3 PARTS =>query execution across three fields: All fields – general SNN and dataset terms. Title/Abstract/Keywords – encoding mechanism terms. Title only – hybrid ANN–SNN relationship terms. Filters Applied: Year range: 2015–2025 Language: English Access type: Open Access | G29: "D:\MyMasterDegreeJourney\Second year\Semester 1\Graduation research\Research logs\Q5" | H29: scidir_q5.bib
A30: SpringerLink | B30: Q5 | C30: =_xlfn.XLOOKUP("Q5",queries!A6, queries!D6) -> ("Spiking neural network*" OR "SNN" OR "neuromorphic network*" OR "deep spiking network*" OR "pulsed neural network*" OR "event-driven neural network" OR "event-based spiking network") AND ("Hybrid ANN-SNN" OR "ANN-SNN conversion" OR "hybrid neural network*" OR "hybrid spiking network*" OR "artificial and spiking neural network*") AND ("event-based dataset*" OR "DVS Gesture" OR "N-MNIST" OR "SHD" OR "Spiking Heidelberg Digits" OR "CIFAR-10-DVS" OR "neuromorphic benchmark") AND ("TTFS" OR "time-to-first-spike" OR "static" OR "hand-crafted" OR "conventional" OR "rule-based" OR "traditional encoding" OR "rate" OR "temporal encoding" OR "population encoding" OR "direct encoding" OR "latency" OR "fixed threshold" OR "non-adaptive" OR "Poisson") | D30: 6 | E30: 45967 | F30: Filters Applied: Content Type: Article, Research Article, Conference Paper, Review Article Language: English Access Type: Open Access Publication Year Range: 2015 – 2025 | G30: "D:\MyMasterDegreeJourney\Second year\Semester 1\Graduation research\Research logs\Q5" | H30: springer_q5.bib
A31: arXiv.org | B31: Q5 | C31: =_xlfn.XLOOKUP("Q5",queries!A6, queries!D6) -> ("Spiking neural network*" OR "SNN" OR "neuromorphic network*" OR "deep spiking network*" OR "pulsed neural network*" OR "event-driven neural network" OR "event-based spiking network") AND ("Hybrid ANN-SNN" OR "ANN-SNN conversion" OR "hybrid neural network*" OR "hybrid spiking network*" OR "artificial and spiking neural network*") AND ("event-based dataset*" OR "DVS Gesture" OR "N-MNIST" OR "SHD" OR "Spiking Heidelberg Digits" OR "CIFAR-10-DVS" OR "neuromorphic benchmark") AND ("TTFS" OR "time-to-first-spike" OR "static" OR "hand-crafted" OR "conventional" OR "rule-based" OR "traditional encoding" OR "rate" OR "temporal encoding" OR "population encoding" OR "direct encoding" OR "latency" OR "fixed threshold" OR "non-adaptive" OR "Poisson") | D31: 2 | E31: 45967 | F31: advanced search across all fields (title, abstract, keywords, and full text); custom dates (2015-2025) | G31: "D:\MyMasterDegreeJourney\Second year\Semester 1\Graduation research\Research logs\Q5" | H31: arxiv_q5.bib
A32: IEEE Xplore | B32: Q6 | C32: =_xlfn.XLOOKUP("Q6",queries!A7, queries!D7) -> ("Spiking neural network*" OR "SNN" OR "neuromorphic network*" OR "deep spiking network*" OR "pulsed neural network*" OR "event-driven neural network" OR "event-based spiking network") AND ("Hybrid ANN-SNN" OR "ANN-SNN conversion" OR "hybrid neural network*" OR "hybrid spiking network*" OR "artificial and spiking neural network*") AND ("software simulation" OR "neuromorphic hardware" OR "Loihi" OR "SpiNNaker" OR "TrueNorth" OR "BindsNET" OR "snnTorch" OR "neuromorphic simulator") | D32: 0 | E32: 45967 | F32: 18 after open access filter produce no result | G32: "D:\MyMasterDegreeJourney\Second year\Semester 1\Graduation research\Research logs\Q6" | H32: ieee_q6.bib
A33: ACM Digital Library | B33: Q6 | C33: =_xlfn.XLOOKUP("Q6",queries!A7, queries!D7) -> ("Spiking neural network*" OR "SNN" OR "neuromorphic network*" OR "deep spiking network*" OR "pulsed neural network*" OR "event-driven neural network" OR "event-based spiking network") AND ("Hybrid ANN-SNN" OR "ANN-SNN conversion" OR "hybrid neural network*" OR "hybrid spiking network*" OR "artificial and spiking neural network*") AND ("software simulation" OR "neuromorphic hardware" OR "Loihi" OR "SpiNNaker" OR "TrueNorth" OR "BindsNET" OR "snnTorch" OR "neuromorphic simulator") | D33: 30 | E33: 45967 | F33: 2015- 2025 | G33: "D:\MyMasterDegreeJourney\Second year\Semester 1\Graduation research\Research logs\Q6" | H33: acm_q6.bib
A34: Scopus | B34: Q6 | C34: =_xlfn.XLOOKUP("Q6",queries!A7, queries!D7) -> ("Spiking neural network*" OR "SNN" OR "neuromorphic network*" OR "deep spiking network*" OR "pulsed neural network*" OR "event-driven neural network" OR "event-based spiking network") AND ("Hybrid ANN-SNN" OR "ANN-SNN conversion" OR "hybrid neural network*" OR "hybrid spiking network*" OR "artificial and spiking neural network*") AND ("software simulation" OR "neuromorphic hardware" OR "Loihi" OR "SpiNNaker" OR "TrueNorth" OR "BindsNET" OR "snnTorch" OR "neuromorphic simulator") | D34: 7 | E34: 45967 | F34: Field searched: (title, abstract, and keywords), (2015-2025), open access, english | G34: "D:\MyMasterDegreeJourney\Second year\Semester 1\Graduation research\Research logs\Q6" | H34: scopus_q6.bib
A35: ScienceDirect | B35: Q6 | C35: "Spiking neural network" OR "SNN" OR "neuromorphic network" OR "deep spiking network" OR "pulsed neural network" OR "event-driven neural network" OR "event-based spiking network" "software simulation" OR "neuromorphic hardware" OR "Loihi" OR "SpiNNaker" OR "TrueNorth" OR "BindsNET" OR "snnTorch" OR "neuromorphic simulator" "Hybrid ANN-SNN" OR "ANN-SNN conversion" OR "hybrid neural network" OR "hybrid spiking network" OR "artificial and spiking neural network" | D35: 1 | E35: 45967 | F35: Q5: 3 PARTS =>query execution across three fields: All fields – general SNN terms. Title/Abstract/Keywords – software simulation terms. Title only – hybrid ANN–SNN relationship terms. Filters Applied: Year range: 2015–2025 Language: English Access type: Open Access | G35: "D:\MyMasterDegreeJourney\Second year\Semester 1\Graduation research\Research logs\Q6" | H35: scidir_q6.bib
A36: SpringerLink | B36: Q6 | C36: =_xlfn.XLOOKUP("Q6",queries!A7, queries!D7) -> ("Spiking neural network*" OR "SNN" OR "neuromorphic network*" OR "deep spiking network*" OR "pulsed neural network*" OR "event-driven neural network" OR "event-based spiking network") AND ("Hybrid ANN-SNN" OR "ANN-SNN conversion" OR "hybrid neural network*" OR "hybrid spiking network*" OR "artificial and spiking neural network*") AND ("software simulation" OR "neuromorphic hardware" OR "Loihi" OR "SpiNNaker" OR "TrueNorth" OR "BindsNET" OR "snnTorch" OR "neuromorphic simulator") | D36: 13 | E36: 45967 | F36: Filter: Open Access. (2015,2025) | G36: "D:\MyMasterDegreeJourney\Second year\Semester 1\Graduation research\Research logs\Q6" | H36: springer_q6.bib
A37: arXiv.org | B37: Q6 | C37: =_xlfn.XLOOKUP("Q6",queries!A7, queries!D7) -> ("Spiking neural network*" OR "SNN" OR "neuromorphic network*" OR "deep spiking network*" OR "pulsed neural network*" OR "event-driven neural network" OR "event-based spiking network") AND ("Hybrid ANN-SNN" OR "ANN-SNN conversion" OR "hybrid neural network*" OR "hybrid spiking network*" OR "artificial and spiking neural network*") AND ("software simulation" OR "neuromorphic hardware" OR "Loihi" OR "SpiNNaker" OR "TrueNorth" OR "BindsNET" OR "snnTorch" OR "neuromorphic simulator") | D37: 9 | E37: 45967 | F37: Queried the Abstract field only; (2015-2025) | G37: "D:\MyMasterDegreeJourney\Second year\Semester 1\Graduation research\Research logs\Q6" | H37: arxiv_q6.bib
A38: IEEE Xplore | B38: Q7 | C38: =_xlfn.XLOOKUP("Q7",queries!A8, queries!D8) -> ("Spiking neural network*" OR "SNN" OR "neuromorphic network*" OR "deep spiking network*" OR "pulsed neural network*" OR "event-driven neural network" OR "event-based spiking network") AND ( "Learnable encoding" OR "Adaptive encoding" OR "learnable spike encoding" OR "adaptive spike encoding" OR "trainable encoder" OR "differentiable encoding" OR "plastic encoding" OR "adaptive threshold encoding" OR "learnable threshold" OR "surrogate gradient") | D38: 7 | E38: 45980 | F38: search All ; Filters Applied: open access only+ Articles 01/01/2015 - 11/19/2025 | G38: "D:\MyMasterDegreeJourney\Second year\Semester 1\Graduation research\Research logs\Q7" | H38: ieee_q7.bib
A39: ACM Digital Library | B39: Q7 | C39: =_xlfn.XLOOKUP("Q7",queries!A8, queries!D8) -> ("Spiking neural network*" OR "SNN" OR "neuromorphic network*" OR "deep spiking network*" OR "pulsed neural network*" OR "event-driven neural network" OR "event-based spiking network") AND ( "Learnable encoding" OR "Adaptive encoding" OR "learnable spike encoding" OR "adaptive spike encoding" OR "trainable encoder" OR "differentiable encoding" OR "plastic encoding" OR "adaptive threshold encoding" OR "learnable threshold" OR "surrogate gradient") | D39: 6 | E39: 45980 | F39: (1) All fields – spiking or neuromorphic neural network terms, (2) Abstract – learnable/adaptive encoding terms. 01/01/2015 - 11/19/2025 | G39: "D:\MyMasterDegreeJourney\Second year\Semester 1\Graduation research\Research logs\Q7"
A40: Scopus | B40: Q7 | C40: ( TITLE-ABS-KEY ( "Spiking neural network*" OR SNN OR "neuromorphic network*" OR "deep spiking network*" OR "pulsed neural network*" OR "event-driven neural network" OR "event-based spiking network" ) ) AND ( ABS ( "Learnable encoding" OR "Adaptive encoding" OR "learnable spike encoding" OR "adaptive spike encoding" OR "trainable encoder" OR "differentiable encoding" OR "plastic encoding" OR "adaptive threshold encoding" OR "learnable threshold" ) ) AND PUBYEAR > 2014 AND PUBYEAR < 2026 AND ( LIMIT-TO ( OA , "all" ) ) AND ( LIMIT-TO ( LANGUAGE , "English" ) ) | D40: 3 | E40: 45980 | F40: (1) TITLE-ABS-KEY – spiking or neuromorphic neural network terms, (2) Abstract – learnable/adaptive encoding terms. 2015 - 2026 , English | G40: "D:\MyMasterDegreeJourney\Second year\Semester 1\Graduation research\Research logs\Q7"
A41: ScienceDirect | B41: Q7 | C41: ("Spiking neural network*" OR "SNN" OR "neuromorphic network*" OR "deep spiking network*" OR "pulsed neural network*" OR "event-driven neural network" OR "event-based spiking network" ) ("Learnable encoding" OR "Adaptive encoding" OR "learnable spike encoding" OR "adaptive spike encoding" OR "trainable encoder" OR "differentiable encoding" OR "plastic encoding" OR "adaptive threshold encoding" OR "learnable threshold") | D41: 0 | E41: 45980 | F41: (1) All fields – spiking or neuromorphic neural network terms, (2) Abstract and title – learnable/adaptive encoding terms. 2015 - 2025 All results not open access | G41: "D:\MyMasterDegreeJourney\Second year\Semester 1\Graduation research\Research logs\Q7"
A42: SpringerLink | B42: Q7 | C42: ("Spiking neural network*" OR "SNN" OR "neuromorphic network*" OR "deep spiking network*" OR "pulsed neural network*" OR "event-driven neural network" OR "event-based spiking network") AND ( "Learnable encoding" OR "Adaptive encoding" OR "learnable spike encoding" OR "adaptive spike encoding" OR "trainable encoder" OR "differentiable encoding" OR "plastic encoding" OR "adaptive threshold encoding" OR "learnable threshold") | D42: 2 | E42: 45980 | F42: (1) All fields – spiking or neuromorphic neural network terms, (2) Abstract – learnable/adaptive encoding terms. 01/01/2015 - 11/19/2025 | G42: "D:\MyMasterDegreeJourney\Second year\Semester 1\Graduation research\Research logs\Q7"
A43: arXiv.org | B43: Q7 | C43: ("Spiking neural network*" OR "SNN" OR "neuromorphic network*" OR "deep spiking network*" OR "pulsed neural network*" OR "event-driven neural network" OR "event-based spiking network") AND ( "Learnable encoding" OR "Adaptive encoding" OR "learnable spike encoding" OR "adaptive spike encoding" OR "trainable encoder" OR "differentiable encoding" OR "plastic encoding" OR "adaptive threshold encoding" OR "learnable threshold") | D43: 8 | E43: 45980 | F43: (1) All fields – spiking or neuromorphic neural network terms, (2) Abstract – learnable/adaptive encoding terms. 01/01/2015 - 11/19/2025 | G43: "D:\MyMasterDegreeJourney\Second year\Semester 1\Graduation research\Research logs\Q7"
D44: Imported References
A45: Number of papers from each database | D45: =SUM(D2:D43) -> 433
A46: IEEE Xplore | B46: {=SUMPRODUCT(--(TRIM(CLEAN(SUBSTITUTE($A$2:$A$43,CHAR(160)," ")))="IEEE Xplore"), --$D$2:$D$43)} -> 55 | D46: Total Duplicates: 193 Resolved: 12 Not Duplicate: 2 Deleted: 179
A47: Scopus | B47: {=SUMPRODUCT(--(TRIM(CLEAN(SUBSTITUTE($A$2:$A$43,CHAR(160)," ")))="Scopus"), --$D$2:$D$43)} -> 86 | D47: TA Screening
A48: ACM Digital Library | B48: {=SUMPRODUCT(--(TRIM(CLEAN(SUBSTITUTE($A$2:$A$43,CHAR(160)," ")))="ACM Digital Library"), --$D$2:$D$43)} -> 120 | D48: Deduplicate: 254 Excluded: 210 Maybe: 0 Included: 44
A49: ScienceDirect | B49: {=SUMPRODUCT(--(TRIM(CLEAN(SUBSTITUTE($A$2:$A$43,CHAR(160)," ")))="ScienceDirect"), --$D$2:$D$43)} -> 20 | D49: Full text Screening
A50: SpringerLink | B50: =SUMIF($A$2:$A$43,"SpringerLink",$D$2:$D$43) -> 95 | D50: Included: 19
A51: arXiv.org | B51: =SUMIF($A$2:$A$43,"arXiv.org",$D$2:$D$43) -> 57
A52: Total | B52: =SUM(B46:B51) -> 433 | D52: So 19 papers got to Data Extraction and quality Assessment stage

Sheet inclusion criteria
A1: No. | B1: Inclusion Criterion | C1: Rationale (why)
A2: i1 | B2: Publication Type: Peer-reviewed journal/conference papers; arXiv preprintst. | C2: This ensures scientific rigor by including only peer-reviewed publications, as well as arXiv preprints that are subjected to manual quality assessment during the review process.
A3: i2 | B3: Language: English | C3: English-language restriction guarantees consistency in interpretation and quality assessment while avoiding translation bias. Nearly all core SNN research is published in English.
A4: i3 | B4: Domain: Studies on SNNs or hybrid ANN--SNN systems. | C4: Ensures inclusion of studies that explicitly integrate both artificial and spiking neural elements, highlighting approaches where ANN and SNN parts interact functionally (rather than being compared separately). This captures the core objective of investigating hybridized, cooperative learning frameworks.
A5: i4 | B5: Focus: Proposes, compares, or evaluates learnable/adaptive spike-encoding methods. | C5: Targets studies contributing novel or comparative insights into adaptive encoding strategies, aligning directly with the main research questions on learnability and adaptation.
A6: i5 | B6: Accessibility: Studies that are fully accessible to the public, with complete full-text available online without subscription or institutional login (i.e., openly accessible to any reader). | C6: Ensures transparency, verifiability, and reproducibility of findings by restricting inclusion to open-access literature that can be independently examined.
A7: i6 | B7: Time Range: 2015-2025 | C7: Limits the corpus to a relevant modern decade of SNN research, capturing advances in hybrid ANN–SNN integration and learnable encoding emerging after major deep-learning breakthroughs.

Sheet exclusion criteria
A1: No. | B1: Exclusion Criterion | C1: Rationale (why)
A2: e1 | B2: Publication Type: Books, theses, editorials, non-peer-reviewed workshop papers. | C2: Excludes materials lacking formal peer review or research validation to ensure only rigorously evaluated scientific contributions are considered.
A3: e2 | B3: Language: Non-English publications. | C3: Eliminates translation bias and ensures consistent interpretation and quality assessment, since most primary SNN studies are published in English.
A4: e3 | B4: Domain: Works unrelated to spiking neural networks, hybrid ANN–SNN systems, or spike-based processing. | C4: Focuses solely on a pure SNN or ANN without any integration, or cooperation between spiking and non-spiking components.
A5: e4 | B5: Focus: Studies using only fixed, rule-based encoding without learnable components, or papers focused solely on hardware implementation without discussing spike-encoding methods. | C5: Excludes works that use fixed or rule-based encoding with no learnable or adaptive mechanism, or that focus solely on hardware or implementation aspects without addressing spike-encoding methods.
A6: e5 | B6: Accessibility: Publications behind paywalls, requiring institutional or paid access, or providing only abstracts or partial previews. | C6: Guarantees transparency and reproducibility by including only fully accessible, verifiable studies that can be independently reviewed.
A7: e6 | B7: Time Range: Publications prior to 2015. | C7: Restricts the scope to the modern era of deep learning–driven SNN and hybrid ANN–SNN research, ensuring the inclusion of up-to-date and methodologically relevant studies.

Sheet QA rubrics
A1: Criterion Group | B1: Assessment Question | C1: Scoring Guide | D1: Where to Look
A2: QA1. Purpose & Context | B2: Are the study’s aim and research context (domain, data, environment) clearly described? | C2: 0 = Unclear 1 = Partially clear 2 = Clearly stated & contextualized | D2: Abstract, Introduction, Problem Statement
A3: QA2. Methodological Quality | B3: Is the study design or methodology appropriate and well explained? | C3: 0 = Unclear 1 = Mentioned 2 = Clearly described & justified | D3: Methods, Model Architecture, Preprocessing
A4: QA3. Data & Tools Transparency | B4: Are datasets, tools, or code identified and accessible? | C4: 0 = None 1 = Mentioned only 2 = Publicly available / detailed | D4: Dataset section, Implementation details, GitHub
A5: QA4. Rigor & Validity | B5: Are threats to validity or methodological limitations acknowledged or mitigated? | C5: 0 = Absent 1 = Briefly mentioned 2 = Systematically addressed | D5: Discussion, Threats to Validity, Ablation
A6: QA5. Results & Interpretation | B6: Are results reported clearly and interpreted in light of prior work or limitations? | C6: 0 = Weak 1 = Basic 2 = Comprehensive & critical | D6: Results, Experiments, Tables/Figures
A7: QA6. Contribution & Credibility | B7: Is the contribution novel, useful, and published in a credible venue? | C7: 0 = Low 1 = Moderate 2 = High / peer-reviewed source | D7: Introduction (Contributions), Abstract, Conclusion
A10: Total Possible Score: 12
A11: Interpretation: | B11: 0–4 = Low quality (consider exclusion)
B12: 5–8 = Moderate quality (include with caution)
B13: 9–12 = High quality (strong evidence base)

Sheet data extraction & scores
A1: Rayyan_key | B1: My_Key | C1: Year | D1: Title | E1: Abstract | F1: Author | G1: Publication Title | H1: DOI | I1: Url | J1: RQ1a_Encoding_Type | K1: RQ1b_Learnable_encoding_parameters | L1: RQ1c_Training_mechanism | M1: RQ1d_Hybrid_Integration_Type | N1: RQ2a_spike_wise_efficiency | O1: RQ2b_Resource_efficiency | P1: RQ2c_Training_Behavior | Q1: RQ2d_Model_Behavior | R1: RQ3a_Dataset_modality | S1: RQ3b_Input_Representation | T1: RQ3c_Datasets_Used | U1: RQ3d_Task_or_Domain | V1: RQ3e_Evaluation_Metrics | W1: RQ4a_Limitation_Category | X1: RQ4b_Reported_Limitations | Y1: RQ4c_Research_Gaps | Z1: hardware_or_simulator | AA1: paper_type | AB1: Architecture_Type | AC1: code_availability | AD1: training_config_short | AE1: QA1. Purpose & Context | AF1: QA2. Methodological Quality | AG1: QA3. Data & Tools Transparency | AH1: QA4. Rigor & Validity | AI1: QA5. Results & Interpretation | AJ1: QA6. Contribution & Credibility | AK1: Total QA Score
A2: rayyan-388589274 | B2: P01 | C2: 2024 | D2: Accurate and {Efficient} {Event}-based {Semantic} {Segmentation} {Using} {Adaptive} {Spiking} {Encoder}-{Decoder} {Network} | E2: Spiking Neural Networks (SNNs) have piqued researchers' interest because of their capacity to process temporal information and low power consumption. However, current state-of-the-art methods limited their biological plausibility and performance because their neurons are generally built on the simple Leaky-Integrate-and-Fire (LIF) model. Due to the high level of dynamic complexity, modern neuron models have seldom been implemented in SNN practice. In this study, we adopt the Phase Plane Analysis (PPA) technique, a technique often utilized in neurodynamics field, to integrate a recent neuron model, namely, the Izhikevich neuron. Based on the findings in the advancement of neuroscience, the Izhikevich neuron model can be biologically plausible while maintaining comparable computational cost with LIF neurons. By utilizing the adopted PPA, we have accomplished putting neurons built with the modified Izhikevich model into SNN practice, dubbed as the Standardized Izhikevich Tonic (SIT) neuron. For performance, we evaluate the suggested technique for image classification tasks in self-built LIF-and-SIT-consisted SNNs, named Hybrid Neural Network (HNN) on static MNIST, Fashion-MNIST, CIFAR-10 datasets and neuromorphic N-MNIST, CIFAR10-DVS, and DVS128 Gesture datasets. The experimental results indicate that the suggested method achieves comparable accuracy while exhibiting more biologically realistic behaviors on nearly all test datasets, demonstrating the efficiency of this novel strategy in bridging the gap between neurodynamics and SNN practice. | F2: Zhang, Rui; Leng, Luziwei; Che, Kaiwei; Zhang, Hu; Cheng, Jie; Guo, Qinghai; Liao, Jiangxing; Cheng, Ran | G2: Optics Express | H2: 10.48550/arXiv.2304.11857 | I2: http://arxiv.org/abs/2304.11857 | J2: learnable and adaptive encoding | K2: Synaptic weights Temporal decay parameters | L2: Surrogate gradient | M2: Pure SNN architecture | N2: Sparse spike activity Reduced firing rate Stable spike behavior Efficient Timesteps | O2: Reduced computational operations Multiplication-free inference (MFI) Energy efficiency computation Memory-efficient | P2: Stable Smoothness | Q2: Robustness Generalization Performance | R2: Vision | S2: Event streams Grayscale images RGB images | T2: DDD17 DSEC-Semantic | U2: Semantic Segmentation task | V2: # Timesteps # Params MIoU # Add # Mult Energy | W2: Architectural Limitations Theoretical Limitations Hardware Limitations Energy Estimation Limitations Optimization Limitations | X2: Suboptimal Sparsity/Architecture Lacks Deep Theoretical Justification Theoretical Energy Estimates Only No Neuromorphic Hardware Deployment No Real-World/Practical Deployment Early-Stage Architecture Search Sensitivity | Y2: Neuromorphic Hardware Deployment Real-World Application AiLIF Theoretical Justification SNN Sparsity Optimization | Z2: GPU \CPU CMOS energy model | AA2: Architecture proposal | AB2: Spiking Encoder-Decoder Network | AC2: Promised. | AD2: Neuron: LIF Method: Direct SNN Training (Spatio-Temporal BP + Dspike) Optimizer: Adam (Poly LR Decay) Loss: Per-pixel Cross-Entropy Epochs: Search: 20, Retraining: 50–100 Inference: Single Time-Step Input: SBT (Δt = 50ms, n = 5) | AE2: 2 | AF2: 2 | AG2: 1 | AH2: 2 | AI2: 2 | AJ2: 2 | AK2: =SUM(AE2:AJ2) -> 11
A3: rayyan-388589102 | B3: P02 | C3: 2024 | D3: Brain-Inspired Architecture for Spiking Neural Networks | E3: Spiking neural networks inherently rely on the precise timing of discrete spike events for information processing. Incorporating additional bio-inspired degrees of freedom, such as trainable synaptic transmission delays and adaptive firing thresholds, is essential for fully leveraging the temporal dynamics of SNNs. Although recent methods have demonstrated the benefits of training synaptic weights and delays, both in terms of accuracy and temporal representation, these techniques typically rely on discrete-time simulations, surrogate gradient approximations, or full access to internal state variables such as membrane potentials. Such requirements limit training precision and efficiency and pose challenges for neuromorphic hardware implementation due to increased memory and I/O bandwidth demands. To overcome these challenges, we propose an analytical event-driven learning framework that computes exact loss gradients not only with respect to synaptic weights and transmission delays but also to adaptive neuronal firing thresholds. Experiments on multiple benchmarks demonstrate significant gains in accuracy (up to 7\%), timing precision, and robustness compared to existing methods. | F3: Tang, Fengzhen; Zhang, Junhuai; Zhang, Chi; Liu, L. | G3: IEEE Access | H3: 10.3390/biomimetics9100646 | I3: https://www.scopus.com/inward/record.uri?eid=2-s2.0-85207676241&doi=10.3390%2Fbiomimetics9100646&partnerID=40&md5=95d33efc0ee7f21bb0c689694d93de73 | J3: learnable and adaptive encoding | K3: Synaptic weights | L3: Surrogate gradient | M3: Pure SNN architecture | N3: Efficient Timesteps Reduced firing rate | O3: Reduced computational operations Energy efficiency computation Memory-efficient | P3: Stable Convergence Randomness reduced | Q3: Robustness Generalization Performance | R3: Vision | S3: Grayscale images RGB images | T3: MNIST Fashion-MNIST CIFAR-10 | U3: Classification task | V3: Accuracy # Timesteps | W3: Biological Limitations Generalizability Limitations Hardware Limitations | X3: Limited exploitation of biological mechanisms Absence of lateral interactions and recurrent connectivity Evaluated only on image classification tasks No Neuromorphic Hardware Deployment | Y3: Extension to more biologically realistic learning rules Inclusion of lateral/recurrent connections Application to speech and time-series tasks | Z3: GPU \CPU | AA3: Architecture proposal | AB3: Convolutional Spiking Neural Network (Conv-SNN) | AC3: Not Available | AD3: Neuron: IF, LIF Random weight initialization Dropout = 40% in fully connected layers Batch normalization (BN) Loss: Loss function = L2 norm (MSE) Method: Surrogate gradient comparison Optimizer: Adam (sigmoid vs arctan) Recommended α = 4.0 30 epochs MNIST: LR = 0.0002, Batch size = 128, Epochs = 60, Surrogate gradient = Atan Fashion-MNIST: LR = 0.0005, Batch size = 128, Epochs = 120, Surrogate gradient = Atan CIFAR10: LR = 0.0001, Batch size = 32, Epochs = 140, Surrogate gradient = Sigmoid | AE3: 2 | AF3: 1 | AG3: 1 | AH3: 1 | AI3: 2 | AJ3: 1 | AK3: =SUM(AE3:AJ3) -> 8
A4: rayyan-378478369 | B4: P03 | C4: 2024 | D4: Brain-Inspired Spiking Neural Networks in {{Engineering Mechanics}}: A New Physics-Based Self-Learning Framework for Sustainable {{Finite Element}} Analysis | E4: Abstract Human visual neurons rely on event-driven, energy-efficient spikes for communication, while silicon image sensors do not. The energy-budget mismatch between biological systems and machine vision technology has inspired the development of artificial visual neurons for use in spiking neural network (SNN). However, the lack of multiplexed data coding schemes reduces the ability of artificial visual neurons in SNN to emulate the visual perception ability of biological systems. Here, we present an artificial visual spiking neuron that enables rate and temporal fusion (RTF) coding of external visual information. The artificial neuron can code visual information at different spiking frequencies (rate coding) and enables precise and energy-efficient time-to-first-spike (TTFS) coding. This multiplexed sensory coding scheme could improve the computing capability and efficacy of artificial visual neurons. A hardware-based SNN with the RTF coding scheme exhibits good consistency with real-world ground truth data and achieves highly accurate steering and speed predictions for self-driving vehicles in complex conditions. The multiplexed RTF coding scheme demonstrates the feasibility of developing highly efficient spike-based neuromorphic hardware. | F4: Tandale, Saurabh Balkrishna; Stoffel, Marcus | G4: Neurocomputing | H4: 10.1007/s00366-024-01967-3 | J4: learnable and adaptive encoding | K4: Synaptic weights Temporal decay parameters Membrane thresholds | L4: Surrogate gradient | M4: Hybrid ANN–SNN architecture | N4: Sparse spike activity Reduced firing rate | O4: Energy efficiency computation Memory-efficient Faster infrence | P4: Convergence Higher simulation speed Smoothness | Q4: Robustness Generalization Performance | R4: Real Numbers | S4: Real Numbers | T4: Custom | U4: Regression task | V4: Root Mean Squared Error (RMSE) Energy Simulation speed | W4: Accuracy Limitations Energy Estimation Limitations Generalizability Limitations Hardware Limitations Methodological Limitations | X4: No on-chip training for Xylo-Av2 Energy estimates from KerasSpiking are conjectural and based on simplifying assumptions Low number of online training steps can introduce errors Model evaluated on specific material models | Y4: Extension to broader material laws Large-scale 3D problems Full neuromorphic FEM solvers Real experimental validation. Brain-inspired neural network-enhanced FEM for mechanical BVPs was previously unavailable in literature Limited application of SNNs in FEM solvers | Z4: Xylo-Av2 KerasSpiking GPU \CPU | AA4: Architecture proposal | AB4: Hybrid Recurrent Spiking Neural Network (SNN) | AC4: Not Available | AD4: Neuron: LIF Optimizer: Adam Batch Size: 32 Initial Learning Rate: 1e-4 Maximum Learning Rate: 1e-3 Epochs (Pre-training): <=4000 Learning Rate Schedule: Cyclical, Triangular Mode Activation Function (Output Layer): Soft Plus Pre-training Phase: Combination of data-driven Ld and physics-based Lp loss functions. Online Training: Physics-based Lp only | AE4: 2 | AF4: 2 | AG4: 2 | AH4: 2 | AI4: 2 | AJ4: 1 | AK4: =SUM(AE4:AJ4) -> 11
A5: rayyan-388589111 | B5: P04 | C5: 2024 | D5: Diagnostic Biomarker Discovery from Brain {{EEG}} Data Using {{LSTM}}, Reservoir-{{SNN}}, and {{NeuCube}} Methods in a Pilot Study Comparing Epilepsy and Migraine | E5: Abstract The present study aims to develop a sustainable framework employing brain-inspired neural networks for solving boundary value problems in Engineering Mechanics. Spiking neural networks, known as the third generation of artificial neural networks, are proposed for physics-based artificial intelligence. Accompanied by a new pseudo-explicit integration scheme based on spiking recurrent neural networks leading to a spike-based pseudo explicit integration scheme, the underlying differential equations are solved with a physics-informed strategy. We propose additionally a third-generation spike-based Legendre Memory Unit that handles large sequences. These third-generation networks can be implemented on the coming-of-age neuromorphic hardware resulting in less energy and memory consumption. The proposed framework, although implicit, is viewed as a pseudo-explicit scheme since it requires almost no or fewer online training steps to achieve a converged solution even for unseen loading sequences. The proposed framework is deployed in a Finite Element solver for plate structures undergoing cyclic loading and a Xylo-Av2 SynSense neuromorphic chip is used to assess its energy performance. An acceleration of more than 40\% when compared to classical Finite Element Method simulations and the capability of online training is observed. We also see a reduction in energy consumption down to the thousandth order. | F5: Saeedinia, Samaneh Alsadat; Jahed-Motlagh, Mohammad Reza; Tafakhori, Abbas; Kasabov, Nikola Kirilov | H5: 10.1038/s41598-024-60996-6 | I5: https://www.nature.com/articles/s41598-024-60996-6 | J5: Adaptive encoding | K5: Adaptive (data-driven) parameters | L5: Local learning rule | M5: Pure SNN architecture | N5: Sparse spike activity Efficient Timesteps | O5: Reduced computational operations Energy efficiency computation Memory-efficient Faster infrence | P5: Convergence | Q5: Robustness Performance | R5: Biosignals | S5: Electroencephalogram (EEG) | T5: Custom | U5: Classification task Biomarker discovery | V5: Accuracy Neuron firing patterns Execution time | W5: Accuracy Limitations Computational Constraints Generalizability Limitations Hardware Limitations | X5: Small and imbalanced dataset Overfitting with large reservoirs Lack of large-scale validation No neuromorphic hardware deployment | Y5: Validation on larger Multi-center datasets Early prediction of disease onset; Deployment on neuromorphic hardware Longitudinal EEG analysis | Z5: MATLAB simulation GPU \CPU | AA5: Architecture proposal Novel Encoding Mechanism | AB5: Reservoir-based SNN | AC5: Available | AD5: Neuron: Izhikevich spiking neurons (70% excitatory / 30% inhibitory) Pipeline: raw EEG → adaptive Online Spike Encoding → partially observed reservoir SNN → firing-rate classifier Learning: hybrid local learning (supervised ReSuMe for observed neurons + unsupervised STDP for hidden neurons) Classifier calibration: firing-rate threshold trained on 70% of data Evaluation: leave-one-out cross-validation | AE5: 2 | AF5: 1 | AG5: 1 | AH5: 1 | AI5: 2 | AJ5: 2 | AK5: =SUM(AE5:AJ5) -> 9
A6: rayyan-378477363 | B6: P05 | C6: 2022 | D6: DTS-SNN: Spiking Neural Networks With Dynamic Time-Surfaces | E6: The success of deep networks and recent industry involvement in brain-inspired computing is igniting a widespread interest in neuromorphic hardware that emulates the biological processes of the brain on an electronic substrate. This review explores interdisciplinary approaches anchored in machine learning theory that enable the applicability of neuromorphic technologies to real-world, human-centric tasks. We find that (1) recent work in binary deep networks and approximate gradient descent learning are strikingly compatible with a neuromorphic substrate; (2) where real-time adaptability and autonomy are necessary, neuromorphic technologies can achieve significant advantages over main-stream ones; and (3) challenges in memory technologies, compounded by a tradition of bottom-up approaches in the field, block the road to major breakthroughs. We suggest that a neuromorphic learning framework, tuned specifically for the spatial and temporal constraints of the neuromorphic substrate, will help guiding hardware algorithm co-design and deploying neuromorphic hardware for proactive learning of real-world data. | F6: Yoo, Donghyung; Jeong, Doo Seok | H6: 10.1109/ACCESS.2022.3209671 | J6: learnable and adaptive encoding | K6: Trainable DTS aggregation weights ai | L6: Surrogate gradient | M6: Pure SNN architecture | N6: Activity-driven suppression Activity-driven responsiveness Efficient Timesteps | O6: Reduced computational operations Energy efficiency computation Memory-efficient | P6: Stable | Q6: Performance Robustness | R6: Vision Audio | S6: Event streams | T6: DVS128 Gesture Spiking Heidelberg Dataset (SHD) N-Cars | U6: Classification task Action/Gesture Recognition | V6: Accuracy # Params # Ops # Timesteps | W6: Generalizability Limitations Hardware Limitations Accuracy Limitations | X6: Kernel time constants selected manually Evaluation limited to simple FC SNN No systematic study of kernel behavior across tasks No deployment on real neuromorphic hardware Slight accuracy drop compared to top convolution-based SNNs despite major efficiency gains. | Y6: Fixed (non-learnable) temporal kernels, motivating learnable or adaptive kernel designs. Extension to deeper SNN architectures and neuromorphic tasks beyond classification. Lack of hardware-level neuromorphic validation. | Z6: GPU \CPU | AA6: Novel Encoding Mechanism | AB6: DTS-SNN (Dynamic Time-Surfaces Spiking Neural Network) | AC6: Available | AD6: Neuron: LIF Optimizer: Adam (no weight decay or LR scheduling) Timesteps: 300 (Gesture), 500 (SHD), 100 (N-Cars) Batch sizes: 16, 64, or 256 depending on dataset | AE6: 2 | AF6: 2 | AG6: 1 | AH6: 2 | AI6: 2 | AJ6: 1 | AK6: =SUM(AE6:AJ6) -> 10
A7: rayyan-388589278 | B7: P06 | C7: 2025 | D7: Efficient {ANN}-{SNN} {Conversion} with {Error} {Compensation} {Learning} | E7: The brain-inspired Spiking neural networks (SNN) claim to present advantages for visual classification tasks in terms of energy efficiency and inherent robustness. In this work, we explore the impact on network inter-layer sparsity through neural coding schemes and the intrinsic structural parameters of Leaky Integrate-and-Fire (LIF) neurons, which can be a candidate metric for performance evaluation. Towards this, we perform a comparative study of four critical neural coding schemes: rate coding (poisson coding), latency coding, phase coding, and direct coding, as well as 6 LIF neuron intrinsic parameter options for a total of 24 combined parameter schemes. Specifically, the models were trained using a supervised training algorithm with a surrogate gradient, and two adversarial attacks, Fast Gradient Sign Method (FGSM) and Projected Gradient Descent (PGD) were applied on a CIFAR10 dataset. We identified the sources of interlayer sparsity in SNN, and quantitatively analyzed the differences in sparsity caused by coding schemes, neuron leakage factors and thresholds. Various aspects of network performance were thoroughly considered in this paper, including inference accuracy, adversarial robustness, and energy efficiency. Our results show that latency coding is the optimum choice in achieving the highest adversarial robustness and energy efficient against low intensity attacks, while rate coding offers the best adversarial robustness against medium and high intensity attacks. The maximum deviations of robustness and efficiency between different coding schemes are 9.35% in VGG5 and 13.59% in VGG9. Increasing the sparsity of spike activity by improving the threshold can bring a short-lived adversarial robustness sweet spot, while excessive sparsity due to changes in threshold and leakage can instead reduce the adversarial robustness. The study reveals the advantages and disadvantages, and design space of SNN in various dimensions, allowing researchers to frame their neuromorphic systems in terms of the coding methods, neuron inherent structure, and model learning capabilities. | F7: Liu, Chang; Shen, Jiangrong; Ran, Xuming; Xu, Mingkun; Xu, Qi; Xu, Yi; Pan, Gang | H7: 10.48550/arXiv.2506.01968 | I7: http://arxiv.org/abs/2506.01968 | J7: learnable encoding | K7: Learnable clipping threshold Dual-threshold neuron parameters Membrane potential initialization value | L7: ANN-to-SNN Conversion Method | M7: ANN-to-SNN conversion | N7: Reduced firing rate Efficient Timesteps | O7: Energy efficiency computation Reduced computational operations | P7: Stable | Q7: Performance Inference Robustness | R7: Vision | S7: Grayscale images RGB images | T7: CIFAR-10 CIFAR-100 ImageNet | U7: Classification task | V7: Accuracy # Timesteps Energy | W7: Energy Estimation Limitations Generalizability Limitations | X7: No real neuromorphic hardware deployment (simulation-based) Energy evaluated via analytical SOP/FLOP estimates Method validated only on image classification | Y7: Extension to non-vision modalities On-chip neuromorphic validation Exploration beyond rate-based conversion | Z7: GPU \CPU | AA7: Conversion framework | AB7: Converted deep CNN-based SNN | AC7: Not Available | AD7: Neuron: IF ANN trained with quantized clip-floor-shift activation (learnable λ, L=4–8 recommended) Inference at T = 2–16 time steps | AE7: 2 | AF7: 2 | AG7: 1 | AH7: 1 | AI7: 1 | AJ7: 1 | AK7: =SUM(AE7:AJ7) -> 8
A8: rayyan-378478131 | B8: P07 | C8: 2022 | D8: Encoding Event-Based Data With a Hybrid SNN Guided Variational Auto-encoder in Neuromorphic Hardware - Proceedings of the 2022 Annual Neuro-Inspired Computational Elements Conference | E8: Convolution helps spiking neural networks (SNNs) capture the spatio-temporal structures of neuromorphic (event) data as evident in the convolution-based SNNs (C-SNNs) with the state-of-the-art classification-accuracies on various datasets. However, the efficacy aside, the efficiency of C-SNN is questionable. In this regard, we propose SNNs with novel trainable dynamic time-surfaces (DTS-SNNs) as efficient alternatives to convolution. The novel dynamic time-surface proposed in this work features its high responsiveness to moving objects given the use of the zero-sum temporal kernel that is motivated by the simple cells’ receptive fields in the early stage visual pathway. We evaluated the performance and computational complexity of our DTS-SNNs on three real-world event-based datasets (DVS128 Gesture, Spiking Heidelberg dataset, N-Cars). The results highlight high classification accuracies and significant improvements in computational efficiency, e.g., merely 1.51% behind of the state-of-the-art result on DVS128 Gesture but a $\times 18$ improvement in efficiency. The code is available online (https://github.com/dooseokjeong/DTS-SNN). | F8: Stewart, Kenneth; Danielescu, Andreea; Shea, Timothy; Neftci, Emre | G8: Nature Communications | H8: 10.1145/3517343.3517372 | I8: https://doi.org/10.1145/3517343.3517372 | J8: learnable encoding | K8: Synaptic weights Latent parameters | L8: Surrogate gradient | M8: Hybrid ANN–SNN architecture | N8: Sparse spike activity Activity-driven suppression | O8: Energy efficiency computation | P8: Hardware-induced performance degradation | Q8: Performance Robustness | R8: Vision | S8: Event streams | T8: NMNIST IBM DVSGesture Custom | U8: Classification task | V8: Accuracy Qualitative latent-space evaluation (T-SNE) | W8: Hardware Limitations Accuracy Limitations Generalizability Limitations | X8: Hardware performance degradation Precision-sensitive latent disentanglement Partial hardware deployment Class confusion | Y8: Evaluation on higher-precision neuromorphic hardware Extension to more complex tasks and larger class counts Missing adaptive-encoding comparisons Limited scalability analysis No quantitative energy benchmarks Improved on-chip learning algorithms | Z8: GPU \CPU Loihi | AA8: Novel Algorithmic Framework | AB8: Hybrid Guided Variational Autoencoder with SNN encoder | AC8: Not Available | AD8: Neuron: LIF (∆t = 1 ms) Surrogate gradients (fast sigmoid) Truncated BPTT (100 ms) VAE loss + excitation/inhibition losses GPU training with PyTorch Loihi deployment using SLAYER with quantized spiking μ, Σ | AE8: 2 | AF8: 2 | AG8: 1 | AH8: 1 | AI8: 2 | AK8: =SUM(AE8:AJ8) -> 8
A9: rayyan-378476879 | B9: P08 | C9: 2022 | D9: Enhancing spiking neural networks with hybrid top-down attention | F9: Liu, Faqiang; Zhao, Rong | G9: Nature Communications | H9: 10.3389/fnins.2022.949142 | I9: https://www.scopus.com/inward/record.uri?eid=2-s2.0-85137892057&doi=10.3389%2Ffnins.2022.949142&partnerID=40&md5=1d34793667e99c14b7268a2cc2d1602d | J9: learnable and adaptive encoding | K9: Synaptic weights Membrane thresholds Temporal decay parameters | L9: Surrogate gradient | M9: Hybrid ANN–SNN architecture | N9: Activity-driven suppression Reduced firing rate Sparse spike activity | O9: Reduced computational operations Energy efficiency computation MAC operations reduction | P9: Stable Efficiency | Q9: Performance Robustness Inference Generalization | R9: Vision | S9: Grayscale images RGB images Event streams | T9: CIFAR-10 CIFAR-100 MNIST N-MNIST | U9: Classification task | V9: Accuracy Adversarial robustness (PGD under L∞ constraint) Firing rate # MAC # Params # Timesteps | W9: Hardware Limitations Architectural Limitations Methodological Limitations | X9: Additional ANN introduces extra parameters and computation Attention applied mainly to encoder layer (limited exploration of deeper feedback) No direct deployment or benchmarking on neuromorphic hardware | Y9: End-to-end deployment on neuromorphic chips Extension to non-vision modalities More complex or multi-level attention mechanisms | Z9: GPU \CPU | AA9: Architecture proposal | AB9: Hybrid ANN–SNN (Convolutional SNN with ANN-based top-down attention) | AC9: Available | AD9: Neuron: LIF SGD with momentum 0.9 Batch size 200 Initial LR 0.1 with warm-up Time step Td = 1 ms K = 6 (static) / 10 (neuromorphic) Attention period Tf = 2Td Temperature-scheduled sigmoid (max Te = 6) Loss weight α ∈ {0.01, 0.1} Sparsity coefficients β = 0.40, γ = 0.51. | AE9: 2 | AF9: 1 | AG9: 2 | AH9: 1 | AI9: 2 | AJ9: 2 | AK9: =SUM(AE9:AJ9) -> 10
A10: rayyan-388589281 | B10: P09 | C10: 2023 | D10: Event-{Enhanced} {Multi}-{Modal} {Spiking} {Neural} {Network} for {Dynamic} {Obstacle} {Avoidance} - Proceedings of the 31st {ACM} {International} {Conference} on {Multimedia} | F10: Wang, Yang; Dong, Bo; Zhang, Yuji; Zhou, Yunduo; Mei, Haiyang; Wei, Ziqi; Yang, Xin | G10: npj Unconventional Computing | H10: 10.1145/3581783.3612147 | I10: http://arxiv.org/abs/2310.02361 | J10: learnable and adaptive encoding | K10: Synaptic weights Latent parameters Membrane thresholds | L10: Surrogate gradient | M10: Hybrid ANN–SNN architecture | N10: Sparse spike activity | O10: Reduced computational operations Energy efficiency computation Memory-efficient | P10: Stable Convergence Faster training | Q10: Performance Robustness Inference Generalization | R10: Multimodal | S10: Event streams Laser scans | T10: Custom | U10: Reinforcement learning task | V10: Success rate # Add # Mult | W10: Hardware Limitations Generalizability Limitations | X10: Evaluated only in simulation No real-robot deployment Need more real challenging scenes | Y10: Lack of real-world neuromorphic deployment No UAV or subterranean robot validation Absence of energy benchmarks on hardware | Z10: Gazebo simulator+AA19 GPU \CPU | AA10: Architecture proposal | AB10: Spiking Actor–Critic Architecture | AC10: Not Available | AD10: Neuron: LIF DDPG (Deep Deterministic Policy Gradient (DDPG)) Batch size 256 Learning rate 1e-4 MFDM-LT timestep = 5 Laser 20 Hz, DVS 100 Hz Current decay 0.5, voltage decay 0.75 Population size = 10 | AE10: 2 | AF10: 2 | AG10: 1 | AH10: 2 | AI10: 2 | AJ10: 2 | AK10: =SUM(AE10:AJ10) -> 11
A11: rayyan-388589103 | B11: P10 | C11: 2023 | D11: Feasibility study on the application of a spiking neural network in myoelectric control systems | E11: As the representatives of brain-inspired models at the neuronal level, spiking neural networks (SNNs) have shown great promise in processing spatiotemporal information with intrinsic temporal dynamics. SNNs are expected to further improve their robustness and computing efficiency by introducing top-down attention at the architectural level, which is crucial for the human brain to support advanced intelligence. However, this attempt encounters difficulties in optimizing the attention in SNNs largely due to the lack of annotations. Here, we develop a hybrid network model with a top-down attention mechanism (HTDA) by incorporating an artificial neural network (ANN) to generate attention maps based on the features extracted by a feedforward SNN. The attention map is then used to modulate the encoding layer of the SNN so that it focuses on the most informative sensory input. To facilitate direct learning of attention maps and avoid labor-intensive annotations, we propose a general principle and a corresponding weakly-supervised objective, which promotes the HTDA model to utilize an integral and small subset of the input to give accurate predictions. On this basis, the ANN and the SNN can be jointly optimized by surrogate gradient descent in an end-to-end manner. We comprehensively evaluated the HTDA model on object recognition tasks, which demonstrates strong robustness to adversarial noise, high computing efficiency, and good interpretability. On the widely-adopted CIFAR-10, CIFAR-100, and MNIST benchmarks, the HTDA model reduces firing rates by up to 50% and improves adversarial robustness by up to 10% with comparable or better accuracy compared with the state-of-the-art SNNs. The HTDA model is also verified on dynamic neuromorphic datasets and achieves consistent improvements. This study provides a new way to boost the performance of SNNs by employing a hybrid top-down attention mechanism. © 2022 Elsevier B.V., All rights reserved. | F11: Sun, Antong; Chen, Xiang; Xu, Mengjuan; Zhang, Xu; Chen, Xun | G11: Nature Communications | H11: 10.3389/fnins.2023.1174760 | I11: https://www.scopus.com/inward/record.uri?eid=2-s2.0-85163610018&doi=10.3389%2Ffnins.2023.1174760&partnerID=40&md5=53c52d2393d8869401e9bfcc8cc1524c | J11: Adaptive encoding | K11: Adaptive (data-driven) parameters | L11: Surrogate gradient | M11: Pure SNN architecture | N11: Sparse spike activity Activity-driven suppression | O11: Reduced computational operations Low latency AC-dominant computation Energy efficiency computation | P11: Stable Faster training | Q11: Inference Robustness | R11: Biosignals | S11: Event streams | T11: Custom | U11: Classification task Action/Gesture Recognition | V11: Accuracy Energy # Add # Mult Inference latency Spike release rate (SRR) Statistical significance (ANOVA) | W11: Methodological Limitations Generalizability Limitations Hardware Limitations Architectural Limitations Accuracy Limitations | X11: Single encoding method and neuron model Only steady-state EMG used Evaluated on limited datasets Lower accuracy than some advanced DNN approaches ower/latency are algorithmic estimates only No real neuromorphic hardware deployment | Y11: Exploration of alternative encoding schemes Evaluation on public datasets Inclusion of transition-phase EMG Integration of advanced training strategies On-chip neuromorphic deployment | Z11: GPU \CPU | AA11: Feasibility study | AB11: SNN | AC11: Not Available | AD11: Neuron: LIF Optimizer: Adam Learning rate: 0.1, 0.01 Batch size: 1/8 of training set Loss: cross-entropy Integration window: T=100 θ=0.6 Vthr2=10. | AE11: 1 | AF11: 1 | AG11: 1 | AH11: 1 | AI11: 2 | AJ11: 1 | AK11: =SUM(AE11:AJ11) -> 7
A12: rayyan-378476870 | B12: P11 | C12: 2023 | D12: Hybrid photonic deep convolutional residual spiking neural networks for text classification | E12: Spiking neural networks (SNNs) underlie low-power, fault-tolerant information processing in the brain and could constitute a power-efficient alternative to conventional deep neural networks when implemented on suitable neuromorphic hardware accelerators. However, instantiating SNNs that solve complex computational tasks in-silico remains a significant challenge. Surrogate gradient (SG) techniques have emerged as a standard solution for training SNNs end-to-end. Still, their success depends on synaptic weight initialization, similar to conventional artificial neural networks (ANNs). Yet, unlike in the case of ANNs, it remains elusive what constitutes a good initial state for an SNN. Here, we develop a general initialization strategy for SNNs inspired by the fluctuation-driven regime commonly observed in the brain. Specifically, we derive practical solutions for data-dependent weight initialization that ensure fluctuation-driven firing in the widely used leaky integrate-and-fire neurons. We empirically show that SNNs initialized following our strategy exhibit superior learning performance when trained with SGs. These findings generalize across several datasets and SNN architectures, including fully connected, deep convolutional, recurrent, and more biologically plausible SNNs obeying Dale’s law. Thus fluctuation-driven initialization provides a practical, versatile, and easy-to-implement strategy for improving SNN training performance on diverse tasks in neuromorphic engineering and computational neuroscience. © 2025 Elsevier B.V., All rights reserved. | F12: Zhang, Yahui; Xiang, Shuiying; Jiang, Shuqing; Han, Yanan; Guo, Xingxing; Zheng, Ling; Shi, Yuechun; Hao, Yue | G12: Neuromorphic Computing and Engineering | H12: 10.1364/OE.497218 | I12: https://www.scopus.com/inward/record.uri?eid=2-s2.0-85171286173&doi=10.1364%2FOE.497218&partnerID=40&md5=d082bfb9c3b9bf1049e1e70bccf94a14 | J12: learnable encoding | K12: Synaptic weights | L12: Surrogate gradient | M12: Hybrid ANN–SNN architecture ANN-to-SNN conversion | N12: Efficient Timesteps | O12: Energy efficiency computation | P12: Convergence Performance sensitive to time-step | Q12: Inference | R12: Texts | S12: Word embeddings | T12: MR AG News IMDB Yelp review polarity | U12: Classification task | V12: Accuracy # Timesteps | W12: Generalizability Limitations Hardware Limitations Energy Estimation Limitations | X12: Energy efficiency discussed conceptually without measured neuromorphic power metrics Photonic SNN limited to classifier stage Evaluation limited to text classification benchmarks No direct deployment or benchmarking on neuromorphic hardware | Y12: End-to-end photonic SNN training Deeper photonic integration beyond classifier Broader NLP tasks and multilingual datasets | Z12: GPU \CPU | AA12: Architecture proposal | AB12: Deep convolutional residual spiking neural network (DCRSNN) | AC12: Not Available | AD12: Neuron: LIF surrogate gradient (arctan/softsign/sigmoid) Adam optimizer (lr = 0.001) Batch size 256 Time window T = 1–16 ms 50 epochs | AE12: 1 | AF12: 1 | AG12: 1 | AH12: 1 | AI12: 1 | AJ12: 1 | AK12: =SUM(AE12:AJ12) -> 6
A13: rayyan-378476869 | B13: P12 | C13: 2023 | D13: Hybrid Spiking Fully Convolutional Neural Network for Semantic Segmentation | E13: Abstract Communication by rare, binary spikes is a key factor for the energy efficiency of biological brains. However, it is harder to train biologically-inspired spiking neural networks than artificial neural networks. This is puzzling given that theoretical results provide exact mapping algorithms from artificial to spiking neural networks with time-to-first-spike coding. In this paper we analyze in theory and simulation the learning dynamics of time-to-first-spike-networks and identify a specific instance of the vanishing-or-exploding gradient problem. While two choices of spiking neural network mappings solve this problem at initialization, only the one with a constant slope of the neuron membrane potential at threshold guarantees the equivalence of the training trajectory between spiking and artificial neural networks with rectified linear units. For specific image classification architectures comprising feed-forward dense or convolutional layers, we demonstrate that deep spiking neural network models can be effectively trained from scratch on MNIST and Fashion-MNIST datasets, or fine-tuned on large-scale datasets, such as CIFAR10,~CIFAR100 and PLACES365, to achieve the exact same performance as that of artificial neural networks, surpassing previous spiking neural networks. Our approach accomplishes high-performance classification with less than 0.3 spikes per neuron, lending itself for an energy-efficient implementation. We also show that fine-tuning spiking neural networks with our robust gradient descent algorithm enables their optimization for hardware implementations with low latency and resilience to noise and quantization. | F13: Zhang, Tao; Xiang, Shuiying; Liu, Wenzhuo; Han, Yanan; Guo, Xingxing; Hao, Yue | G13: Frontiers in Neuroscience | H13: 10.3390/electronics12173565 | I13: https://www.scopus.com/inward/record.uri?eid=2-s2.0-85170580778&doi=10.3390%2Felectronics12173565&partnerID=40&md5=beecd9f2e651ee9ddb9cb975c3a8d73e | J13: learnable encoding | K13: Synaptic weights | L13: Surrogate gradient | M13: Hybrid ANN–SNN architecture | O13: AC-dominant computation Energy efficiency computation | P13: Stable Performance sensitive to time-step | Q13: Performance | R13: Vision | S13: RGB images | T13: VOC2012 COCO2017 DRIVE Cityscapes | U13: Semantic Segmentation task | V13: MIoU Pixel Acc # Params Precision Recall F1 Energy | W13: Training scalability Limitations Accuracy Limitations Hardware Limitations Energy Estimation Limitations | X13: Performance inferior to CNNs Sensitive to time-step selection Long training time Lack of pretrained SNN models Energy based on theoretical estimation No direct deployment or benchmarking on neuromorphic hardware | Y13: Lack of pretrained SNN backbones Limited exploration of deeper adaptive encoding No real neuromorphic hardware deployment | Z13: GPU \CPU CMOS energy model | AA13: Architecture proposal | AB13: Hybrid spiking fully convolutional neural network (SFCNN) | AC13: Not Available | AD13: Neuron: IF Time window=6 Simulation time step=1 ms Adam optimizer LR=0.0005 Batch size=8 Cosine LR scheduler Softsign surrogate Cross-entropy loss | AE13: 1 | AF13: 1 | AG13: 2 | AH13: 1 | AI13: 2 | AJ13: 1 | AK13: =SUM(AE13:AJ13) -> 8
A14: rayyan-378478374 | B14: P13 | C14: 2025 | D14: NeuBridge: bridging quantized activations and spiking neurons for ANN-SNN conversion | E14: Abstract Spiking neural networks (SNNs) take inspiration from the brain to enable energy-efficient computations. Since the advent of Transformers, SNNs have struggled to compete with artificial networks on modern sequential tasks, as they inherit limitations from recurrent neural networks (RNNs), with the added challenge of training with non-differentiable binary spiking activations. However, a recent renewed interest in efficient alternatives to Transformers has given rise to state-of-the-art recurrent architectures named state space models (SSMs). This work systematically investigates, for the first time, the intersection of state-of-the-art SSMs with SNNs for long-range sequence modelling. Results suggest that SSM-based SNNs can outperform the Transformer on all tasks of a well-established long-range sequence modelling benchmark. It is also shown that SSM-based SNNs can outperform current state-of-the-art SNNs with fewer parameters on sequential image classification. Finally, a novel feature mixing layer is introduced, improving SNN accuracy while challenging assumptions about the role of binary activations in SNNs. This work paves the way for deploying powerful SSM-based architectures, such as large language models, to neuromorphic hardware for energy-efficient long-range sequence modelling. | F14: Yang, Yuchen; Liu, Jingcheng; Yu, Chengting; Yang, Chengyi; Wang, Gaoang; Wang, Aili | H14: 10.1088/2634-4386/ade183 | I14: https://www.scopus.com/inward/record.uri?eid=2-s2.0-105009129892&doi=10.1088%2F2634-4386%2Fade183&partnerID=40&md5=b67fe63ab11494a23713296aaed1377a | J14: learnable and adaptive encoding | K14: Synaptic weights Temporal decay parameters | L14: ANN-to-SNN Conversion Method | M14: ANN-to-SNN conversion | N14: Reduced spike count | O14: Low latency AC-dominant computation Energy efficiency computation | P14: Stable | Q14: Inference Performance | R14: Vision | S14: Grayscale images RGB images | T14: CIFAR-10 ImageNet | U14: Classification task | V14: Accuracy # Add # Mult # Timesteps Energy | W14: Hardware Limitations Energy Estimation Limitations Generalizability Limitations Methodological Limitations | X14: No physical neuromorphic chip deployment Energy estimated analytically Evaluation limited to vision benchmarks Comparison with adaptive-at-runtime encoding mechanisms2 | Y14: Lack of real neuromorphic hardware validation No evaluation on non-vision modalities Absence of on-chip learning | Z14: GPU \CPU | AA14: Novel Algorithmic Framework | AB14: Converted spiking neural network (LIF-based) | AC14: Available | AD14: Neuron: LIF Quantization-aware ANN training SGD (momentum 0.9) Cross-entropy loss Quantization-aware training Trainable τ ∈ [1, 4] ANN trained first SNN obtained via direct conversion | AE14: 2 | AF14: 2 | AG14: 1 | AH14: 1 | AI14: 1 | AJ14: 2 | AK14: =SUM(AE14:AJ14) -> 9
A15: rayyan-378478161 | B15: P14 | C15: 2023 | D15: Single {{Channel Speech Enhancement Using U-Net Spiking Neural Networks}} | E15: Spiking neural networks (SNNs) offer a promising avenue for energy-efficient computations on neuromorphic hardware, leveraging the unique advantages of spike-based signaling. Despite their potential, SNNs often lag behind artificial neural networks (ANNs) in performance, mainly due to the complexity of effectively translating ANN activation values into the time domain spikes. This challenge arises due to the quantization and unevenness errors that occur when mapping continuous activations to discrete spikes and irregular spike timing. This paper introduces NeuBridge, an innovative ANN-SNN conversion method that utilize adaptive temporal coding to significantly reduce the number of required time steps without compromising accuracy. NeuBridge addresses the errors by employing a decode-encode neuron and adaptive temporal coding, effectively bridging the performance gap between ANNs and SNNs. By establishing an equivalence between quantized ANNs and SNNs and optimizing the temporal coding process, we improve SNN performance with as few as 2 time steps. Empirical evaluations on CIFAR-10 and ImageNet datasets demonstrate that NeuBridge consistently performs better than existing conversion methods in both accuracy and efficiency, achieving high performance within just 3 time steps. NeuBridge code is available at: https://github.com/Intelli-Chip-Lab/NeuBridge. © 2025 Elsevier B.V., All rights reserved. | F15: Riahi, Abir; Plourde, {\'E}ric | G15: Complexity | H15: 10.48550/arXiv.2307.14464 | J15: learnable encoding | K15: Synaptic weights Temporal decay parameters Membrane thresholds | L15: Surrogate gradient | M15: Hybrid ANN–SNN architecture | N15: Sparse spike activity Activity-driven suppression | O15: Energy efficiency computation MAC operations reduction | P15: Stable | Q15: Inference Performance Robustness | R15: Audio | S15: Time-frequency representation | T15: Voice Bank Corpus (VCTK) + DEMAND noise dataset | U15: Regression task Speech enhancement | V15: Perceptual Evaluation of Speech Quality (PESQ) Short-Time Objective Intelligibility (STOI) Deep Noise Suppression Mean Opinion Score (DNSMOS: SIG, BAK, OVRL) | W15: Generalizability Limitations Hardware Limitations Architectural Limitations Methodological Limitations | X15: No physical neuromorphic chip deployment Performance is evaluated using a fixed encoding strategy (direct input encoding). Only a single neuron model (LIF) is considered. A single loss function (log-spectral distance, LSD) is used. The approach relies exclusively on a direct-mapping strategy (no masking-based formulation). No masking-based SNN variant is explored or compared. No neuron model diversity (e.g., IF, adaptive LIF, SRM) is investigated. | Y15: Extension to alternative encoding strategies (e.g., masking, adaptive encoders) Other neuron models Different loss functions Broader speech enhancement scenarios. | Z15: GPU \CPU | AA15: Architecture proposal | AB15: U-Net-based Spiking Neural Network | AC15: Not Available | AD15: Neuron: LIF Adam (lr=0.002, β1=0.5, β2=0.9) Batch size 32 60 epochs Surrogate gradient (ArcTan) Convolution weights ~𝒩(0,0.2) Decay strengths & thresholds initialized from normal distributions. | AE15: 1 | AF15: 1 | AG15: 1 | AH15: 1 | AI15: 1 | AJ15: 1 | AK15: =SUM(AE15:AJ15) -> 6
A16: rayyan-378478320 | B16: P15 | C16: 2022 | D16: SIT: {{A Bionic}} and {{Non-Linear Neuron}} for {{Spiking Neural Network}} | E16: Artificial neural networks (ANNs) have demonstrated outstanding performance in numerous tasks, but deployment in resource-constrained environments remains a challenge due to their high computational and memory requirements. Spiking neural networks (SNNs) operate through discrete spike events and offer superior energy efficiency, providing a bio-inspired alternative. However, current ANN-to-SNN conversion often results in significant accuracy loss and increased inference time due to conversion errors such as clipping, quantization, and uneven activation. This paper proposes a novel ANN-to-SNN conversion framework based on error compensation learning. We introduce a learnable threshold clipping function, dual-threshold neurons, and an optimized membrane potential initialization strategy to mitigate the conversion error. Together, these techniques address the clipping error through adaptive thresholds, dynamically reduce the quantization error through dual-threshold neurons, and minimize the non-uniformity error by effectively managing the membrane potential. Experimental results on CIFAR-10, CIFAR-100, ImageNet datasets show that our method achieves high-precision and ultra-low latency among existing conversion methods. Using only two time steps, our method significantly reduces the inference time while maintains competitive accuracy of 94.75\% on CIFAR-10 dataset under ResNet-18 structure. This research promotes the practical application of SNNs on low-power hardware, making efficient real-time processing possible. | F16: Jin, Cheng; Zhu, Rui-Jie; Wu, Xiao; Deng, Liang-Jian | G16: Biomimetics | H16: 10.48550/arXiv.2203.16117 | J16: learnable encoding | K16: Synaptic weights | L16: Surrogate gradient | M16: Hybrid ANN–SNN architecture | P16: Faster training | R16: Vision | S16: Grayscale images RGB images Event streams | T16: MNIST Fashion-MNIST CIFAR-10 N-MNIS CIFAR10-DVS DVS128 Gesture | U16: Classification task Action/Gesture Recognition | V16: Accuracy | W16: Methodological Limitations Interpretability Limitations Energy Estimation Limitations Hardware Limitations | X16: PPA-based standardization quantitatively resolves only parameter b Other Izhikevich parameters rely on empirical or neuroscience heuristics No neuromorphic hardware deployment or energy evaluation. | Y16: Fully learnable or adaptive neuron parameterization beyond b Hardware-level neuromorphic validation (e.g., Loihi) Explicit energy/spike-efficiency benchmarking Extension beyond vision-classification tasks | Z16: GPU \CPU | AA16: Architecture proposal | AB16: Hybrid CNN-SNN | AC16: Not Available | AD16: Neuron: Izhikevich Surrogate-gradient training Adam (lr = 0.01) with cosine annealing Batch = 16 τ = 2 simulation steps T = 8–20 depending on dataset SIT neurons inserted into selected convolutional layers. | AE16: 2 | AF16: 2 | AG16: 1 | AH16: 2 | AI16: 2 | AJ16: 2 | AK16: =SUM(AE16:AJ16) -> 11
A17: rayyan-388589280 | B17: P16 | C17: 2025 | D17: Spike {Encoding} for {Environmental} {Sound}: {A} {Comparative} {Benchmark} | E17: Despite the maturity and availability of speech recognition systems, there are few available spiking speech recognition tasks that can be implemented with current neuromorphic systems. The methods used previously to generate spiking speech data are not capable of encoding speech in real-time or encoding very large modern speech datasets efficiently for input to neuromorphic processors. The ability to efficiently encode audio data to spikes will enable a wider variety of spiking audio datasets to be available and can also enable algorithmic development of real-time neuromorphic automatic speech recognition systems. Therefore, we developed speech2spikes, a simple and efficient audio processing pipeline that encodes recorded audio into spikes and is suitable for real-time operation with low-power neuromorphic processors. To demonstrate the efficacy of our method for audio to spike encoding we show that a small feed-forward spiking neural network trained on data generated with the pipeline achieves accuracy on the Google Speech Commands recognition task, exceeding the state-of-the art set by Spiking Speech Commands, a prior spiking encoding of the Google Speech Commands dataset, by over 10\%. We also demonstrate a proof-of-concept real-time neuromorphic automatic speech recognition system using audio encoded with speech2spikes streamed to an Intel Loihi neuromorphic research processor. | F17: Larroza, Andres; Naranjo-Alcazar, Javier; Ortiz, Vicent; Zuccarello, Pedro | G17: IEEE Access | H17: 10.48550/arXiv.2503.11206 | I17: http://arxiv.org/abs/2503.11206 | J17: Adaptive encoding | K17: Adaptive (data-driven) parameters | L17: Surrogate gradient | M17: Pure SNN architecture | N17: Reduced firing rate Reduced spike count | O17: Energy efficiency computation | P17: Stable | R17: Audio | S17: 128-band Mel-spectrograms (20–20 kHz) | T17: ESC-10 UrbanSound8K TAU Urban Acoustic Scenes (TAU-3Class) | U17: Classification task Regression task Signal reconstruction | V17: Error in decibels (ERRdB) Signal-to-noise ratio (SNR) Accuracy Firing rate Encoding time Memory usage | W17: Methodological Limitations Architectural Limitations Accuracy Limitations Hardware Limitations | X17: All SNN results remain below ANN baselines No encoder–architecture co-design Fixed SNN architecture not optimized for audio No neuromorphic hardware deployment | Y17: Lack of learnable or gradient-trained spike encoders for environmental audio Need for encoder–architecture co-design Evaluation on neuromorphic hardware Exploration of attention-based SNNs paired with efficient encoders | Z17: GPU \CPU | AA17: Comparative Benchmark Study | AB17: Pure SNN classifier with external spike encoder | AC17: Not Available | AD17: Neuron: LIF Mel-spectrogram => spike encoding (MW / SF / TAE) => FC-SNN (LIF) Batch = 32 Lr = 0.01, 100 epochs Macro-accuracy evaluation | AE17: 1 | AF17: 1 | AG17: 1 | AH17: 1 | AI17: 1 | AJ17: 0 | AK17: =SUM(AE17:AJ17) -> 5
A18: rayyan-378478367 | B18: P17 | C18: 2024 | D18: Spiking Neural Networks for Nonlinear Regression of Complex Transient Signals on Sustainable Neuromorphic Processors | E18: Abstract By mimicking the neurons and synapses of the human brain and employing spiking neural networks on neuromorphic chips, neuromorphic computing offers a promising energy-efficient machine intelligence. How to borrow high-level brain dynamic mechanisms to help neuromorphic computing achieve energy advantages is a fundamental issue. This work presents an application-oriented algorithm-software-hardware co-designed neuromorphic system for this issue. First, we design and fabricate an asynchronous chip called ``Speck'', a sensing-computing neuromorphic system on chip. With the low processor resting power of 0.42mW, Speck can satisfy the hardware requirements of dynamic computing: no-input consumes no energy. Second, we uncover the ``dynamic imbalance'' in spiking neural networks and develop an attention-based framework for achieving the algorithmic requirements of dynamic computing: varied inputs consume energy with large variance. Together, we demonstrate a neuromorphic system with real-time power as low as 0.70mW. This work exhibits the promising potentials of neuromorphic computing with its asynchronous event-driven, sparse, and dynamic nature. | F18: Stoffel, Marcus; Tandale, Saurabh Balkrishna | H18: 10.1038/s44335-024-00002-4 | J18: learnable and adaptive encoding | K18: Synaptic weights Temporal decay parameters Membrane thresholds | L18: Surrogate gradient | M18: Hybrid ANN–SNN architecture | N18: Sparse spike activity | O18: Energy efficiency computation | P18: Slower Stable | Q18: Robustness | R18: Real Numbers | S18: Real Numbers | T18: Custom | U18: Regression task | V18: Root Mean Squared Error (RMSE) Energy | W18: Training scalability Limitations Hardware Limitations Energy Estimation Limitations | X18: Energy values are estimated using KerasSpiking (not direct hardware measurements) Training time of SNNs is longer than ANN counterparts Full deployment on neuromorphic hardware is constrained by dense layers | Y18: Limited prior work on nonlinear regression with SNNs Need for broader application domains and deeper fully spiking architectures Further validation on real neuromorphic hardware beyond partial deployment | Z18: Loihi GPU \CPU | AA18: Novel Algorithmic Framework | AB18: Recurrent Spiking Neural Network (RSNN) | AC18: Not Available | AD18: Neuron: LIF Adam optimizer (lr = 0.001, β₁ = 0.9, β₂ = 0.999) Surrogate-gradient learning Hyperband architecture search RMSE loss | AE18: 2 | AF18: 2 | AG18: 1 | AH18: 2 | AI18: 2 | AJ18: 2 | AK18: =SUM(AE18:AJ18) -> 11
A19: rayyan-388589275 | B19: P18 | C19: 2024 | D19: STAL: Spike Threshold} {Adaptive} {Learning} {Encoder} for {Classification} of {Pain}-{Related} {Biosignal} {Data} | E19: For energy-efficient computation in specialized neuromorphic hardware, we present spiking neural coding, an instantiation of a family of artificial neural models grounded in the theory of predictive coding. This model, the first of its kind, works by operating in a never-ending process of “guess-and-check”, where neurons predict the activity values of one another and then adjust their own activities to make better future predictions. The interactive, iterative nature of our system fits well into the continuous time formulation of sensory stream prediction and, as we show, the model’s structure yields a local synaptic update rule, which can be used to complement or as an alternative to online spike-timing dependent plasticity. In this article, we experiment with an instantiation of our model consisting of leaky integrate-and-fire units. However, the framework within which our system is situated can naturally incorporate more complex neurons such as the Hodgkin-Huxley model. Our experimental results in pattern recognition demonstrate the potential of the model when binary spike trains are the primary paradigm for inter-neuron communication. Notably, spiking neural coding is competitive in terms of classification performance and experiences less forgetting when learning from a task sequence, offering a more computationally economical, biologically-motivated alternative to popular artificial neural networks. | F19: Hens, Freek; Dehshibi, Mohammad Mahdi; Bagheriye, Leila; Shahsavari, Mahyar; Tajadura-Jiménez, Ana | H19: 10.48550/arXiv.2407.08362 | I19: http://arxiv.org/abs/2407.08362 | J19: learnable and adaptive encoding | K19: Synaptic weights Membrane thresholds | L19: Surrogate gradient | M19: Hybrid ANN–SNN architecture | N19: Sparse spike activity | O19: Energy efficiency computation | P19: Stable | Q19: Robustness Performance | R19: Multimodal | S19: Electromyography (EMG) Inertial measurement unit (IMU) | T19: EmoPain dataset | U19: Classification task | V19: Accuracy F1 AUC Matthews Correlation Coefficient (MCC) Spike density | W19: Hardware Limitations Energy Estimation Limitations Generalizability Limitations | X19: Small dataset size and class imbalance Higher spike density for best-performing STAL–Stacked variant No deployment on neuromorphic hardware Performance lower than deep learning models in AUC | Y19: Neuromorphic hardware implementation and benchmarking Extension to multi-level pain intensity and behavior classification Broader biosignal domains Real-world wearable deployment | Z19: GPU \CPU | AA19: Architecture proposal | AB19: Ensemble of Spiking Recurrent Neural Network (SRNN) | AC19: Available | AD19: Neuron: LIF AdamW optimizer LR = 5e-3 (encoder), 7.5e-4 (SRNN) batch sizes {sEMG:32, Energy:8, Angle:16} ψ = 5 spikes/step dropout = 0.5 30 encoder epochs 25 SRNN epochs early stopping LOSO (Leave-One-Subject-Out) cross-validation | AE19: 2 | AF19: 2 | AG19: 1 | AH19: 2 | AI19: 2 | AJ19: 2 | AK19: =SUM(AE19:AJ19) -> 11
A20: rayyan-388589277 | B20: P19 | C20: 2024 | D20: Ternary {Spike}-based {Neuromorphic} {Signal} {Processing} {System} | E20: Autonomous obstacle avoidance is of vital importance for an intelligent agent such as a mobile robot to navigate in its environment. Existing state-of-the-art methods train a spiking neural network (SNN) with deep reinforcement learning (DRL) to achieve energy-efficient and fast inference speed in complex/unknown scenes. These methods typically assume that the environment is static while the obstacles in real-world scenes are often dynamic. The movement of obstacles increases the complexity of the environment and poses a great challenge to the existing methods. In this work, we approach robust dynamic obstacle avoidance twofold. First, we introduce the neuromorphic vision sensor (i.e., event camera) to provide motion cues complementary to the traditional Laser depth data for handling dynamic obstacles. Second, we develop an DRL-based event-enhanced multimodal spiking actor network (EEM-SAN) that extracts information from motion events data via unsupervised representation learning and fuses Laser and event camera data with learnable thresholding. Experiments demonstrate that our EEM-SAN outperforms state-of-the-art obstacle avoidance methods by a significant margin, especially for dynamic obstacle avoidance. | F20: Wang, Shuai; Zhang, Dehao; Belatreche, Ammar; Xiao, Yichen; Qing, Hongyu; We, Wenjie; Zhang, Malu; Yang, Yang | H20: 10.48550/arXiv.2407.05310 | I20: http://arxiv.org/abs/2407.05310 | J20: Adaptive encoding | K20: Adaptive (data-driven) parameters | L20: Surrogate gradient | M20: Pure SNN architecture | N20: Sparse spike activity Reduced firing rate | O20: Energy efficiency computation Memory-efficient Multiplication-free inference (MFI) | P20: Stable | Q20: Robustness Performance | R20: Biosignals Audio | S20: Electroencephalogram (EEG) Raw audio waveform (time-domain signal) | T20: Google Speech Commands(GSC) KUL EEG dataset DTU EEG dataset | U20: Classification task Speech recognition | V20: Accuracy Memory usage Precision(weights / membrane potentials) # Timesteps # Add # Mult Energy | W20: Hardware Limitations Energy Estimation Limitations Generalizability Limitations | X20: Energy evaluation based on theoretical analysis only No real neuromorphic hardware deployment Evaluation limited to speech and EEG tasks | Y20: Deployment on real neuromorphic chips Extension to additional signal modalities On-chip learning validation | Z20: GPU \CPU | AA20: Architecture proposal | AB20: Quantized Ternary Spiking Neural Network (QT-SNN) | AC20: Not Available | AD20: Neuron: LIF STBP; τ = 0.5 Learnable Vth/α₁ => inside the QT-SNN neuron model (not in the encoding stage) α₃/α₁ constrained to powers of two 4 inference timesteps Raw signal → TAE → ternary spikes → QT-SNN; STBP training; learnable threshold scaling & spike amplitude; quantized inference with bit-shift operations | AE20: 2 | AF20: 2 | AG20: 1 | AH20: 2 | AI20: 2 | AJ20: 2 | AK20: =SUM(AE20:AJ20) -> 11
